[
  {
    "id": "aitape_pg",
    "name": "Aitape",
    "location": "-3.13333333333, 142.35",
    "land_region": "",
    "country": "Papua New Guinea",
    "country_code": "PG",
    "functional_area": "",
    "body_of_water": "",
    "code": "aitape_pg",
    "isTerminal": null
  },
  {
    "id": "alotau_pg",
    "name": "Alotau",
    "location": "-10.26261877513262, 150.44999752721822",
    "land_region": "",
    "country": "Papua New Guinea",
    "country_code": "PG",
    "functional_area": "",
    "body_of_water": "",
    "code": "alotau_pg",
    "isTerminal": false
  },
  {
    "id": "anewa_bay_pg",
    "name": "Anewa Bay",
    "location": "-6.12, 155.33",
    "land_region": "",
    "country": "Papua New Guinea",
    "country_code": "PG",
    "functional_area": "",
    "body_of_water": "",
    "code": "anewa_bay_pg",
    "isTerminal": null
  },
  {
    "id": "bialla_pg",
    "name": "Bialla",
    "location": "-5.289060717297393, 151.05474247633117",
    "land_region": "",
    "country": "Papua New Guinea",
    "country_code": "PG",
    "functional_area": "",
    "body_of_water": "",
    "code": "bialla_pg",
    "isTerminal": null
  },
  {
    "id": "buka_pg",
    "name": "Buka",
    "location": "-5.43333333333, 154.666666667",
    "land_region": "",
    "country": "Papua New Guinea",
    "country_code": "PG",
    "functional_area": "",
    "body_of_water": "",
    "code": "buka_pg",
    "isTerminal": null
  },
  {
    "id": "daru_pg",
    "name": "Daru",
    "location": "-8.979863999000973, 143.19999761005982",
    "land_region": "",
    "country": "Papua New Guinea",
    "country_code": "PG",
    "functional_area": "",
    "body_of_water": "",
    "code": "daru_pg",
    "isTerminal": null
  },
  {
    "id": "kavieng_pg",
    "name": "Kavieng",
    "location": "-2.58333333333, 150.8",
    "land_region": "",
    "country": "Papua New Guinea",
    "country_code": "PG",
    "functional_area": "",
    "body_of_water": "",
    "code": "kavieng_pg",
    "isTerminal": false
  },
  {
    "id": "kieta_pg",
    "name": "Kieta",
    "location": "-6.21666666667, 155.633333333",
    "land_region": "",
    "country": "Papua New Guinea",
    "country_code": "PG",
    "functional_area": "",
    "body_of_water": "",
    "code": "kieta_pg",
    "isTerminal": null
  },
  {
    "id": "kimbe_pg",
    "name": "Kimbe",
    "location": "-5.55, 150.15",
    "land_region": "",
    "country": "Papua New Guinea",
    "country_code": "PG",
    "functional_area": "",
    "body_of_water": "",
    "code": "kimbe_pg",
    "isTerminal": false
  },
  {
    "id": "kumul_marine_terminal_pg",
    "name": "Kumul Marine Terminal",
    "location": "-7.65381179994697, 144.37989912880118",
    "land_region": "",
    "country": "Papua New Guinea",
    "country_code": "PG",
    "functional_area": "",
    "body_of_water": "",
    "code": "kumul_marine_terminal_pg",
    "isTerminal": null
  },
  {
    "id": "lae_pg",
    "name": "Lae",
    "location": "-6.71666666667, 146.966666667",
    "land_region": "",
    "country": "Papua New Guinea",
    "country_code": "PG",
    "functional_area": "",
    "body_of_water": "",
    "code": "lae_pg",
    "isTerminal": true
  },
  {
    "id": "lorengau_pg",
    "name": "Lorengau",
    "location": "-2.043917887427037, 147.1518767619375",
    "land_region": "",
    "country": "Papua New Guinea",
    "country_code": "PG",
    "functional_area": "",
    "body_of_water": "",
    "code": "lorengau_pg",
    "isTerminal": null
  },
  {
    "id": "madang_pg",
    "name": "Madang",
    "location": "-5.207922338825873, 145.7913167396493",
    "land_region": "",
    "country": "Papua New Guinea",
    "country_code": "PG",
    "functional_area": "",
    "body_of_water": "",
    "code": "madang_pg",
    "isTerminal": false
  },
  {
    "id": "oro_bay_pg",
    "name": "Oro Bay",
    "location": "-8.89999999999998, 148.483333333",
    "land_region": "",
    "country": "Papua New Guinea",
    "country_code": "PG",
    "functional_area": "",
    "body_of_water": "",
    "code": "oro_bay_pg",
    "isTerminal": false
  },
  {
    "id": "port_moresby_pg",
    "name": "Port Moresby",
    "location": "-9.435030366611562, 147.145388082226",
    "land_region": "",
    "country": "Papua New Guinea",
    "country_code": "PG",
    "functional_area": "",
    "body_of_water": "",
    "code": "port_moresby_pg",
    "isTerminal": true
  },
  {
    "id": "rabaul_pg",
    "name": "Rabaul",
    "location": "-4.19161272884421, 152.177124023437",
    "land_region": "",
    "country": "Papua New Guinea",
    "country_code": "PG",
    "functional_area": "",
    "body_of_water": "",
    "code": "rabaul_pg",
    "isTerminal": true
  },
  {
    "id": "samarai_pg",
    "name": "Samarai",
    "location": "-10.55929572569494, 150.59800772653242",
    "land_region": "",
    "country": "Papua New Guinea",
    "country_code": "PG",
    "functional_area": "",
    "body_of_water": "",
    "code": "samarai_pg",
    "isTerminal": null
  },
  {
    "id": "vanimo_pg",
    "name": "Vanimo",
    "location": "-2.68333333333, 141.3",
    "land_region": "",
    "country": "Papua New Guinea",
    "country_code": "PG",
    "functional_area": "",
    "body_of_water": "",
    "code": "vanimo_pg",
    "isTerminal": null
  },
  {
    "id": "wewak_pg",
    "name": "Wewak",
    "location": "-3.5616505013052, 143.61535542773",
    "land_region": "",
    "country": "Papua New Guinea",
    "country_code": "PG",
    "functional_area": "",
    "body_of_water": "",
    "code": "wewak_pg",
    "isTerminal": false
  }
]