[
  {
    "contentType": "airport",
    "datatype": "airport",
    "id": "26534",
    "ident": "VGHS",
    "type": "large_airport",
    "name": "Hazrat Shahjalal International Airport",
    "regionRef": "306742",
    "continentRef": "302551",
    "municipality": "Dhaka",
    "latitude_deg": "23.843347",
    "longitude_deg": "90.397783",
    "elevation_ft": "30",
    "magnetic_variation_deg": "-0.304",
    "icao_code": "VGHS",
    "iata_code": "DAC",
    "gps_code": "VGHS",
    "local_code": null,
    "has_scheduled_service": "1",
    "score": "1050",
    "home_link": null,
    "wikipedia_link": "https://en.wikipedia.org/wiki/Shahjalal_International_Airport",
    "pilot_link": null,
    "keywords": "VGZR, Zia International Airport, Dacca International Airport, Hazrat Shahjalal International Airport",
    "zoom": "13",
    "changeMemberRef": "330018",
    "changeDate": "2019-01-13 12:00:15",
    "changeType": "update",
    "changeComment": null,
    "airportRef": "26534",
    "visitor_count": "47",
    "comment_count": "12",
    "home_count": "18",
    "region_code": "BD-3",
    "region_name": "Dhaka Division",
    "region_local_code": "3",
    "region_keywords": "Dhaka bibhag",
    "countryRef": "302622",
    "country_code": "BD",
    "country_name": "Bangladesh",
    "country_keywords": "Bangladeshi airports",
    "continent_code": "AS",
    "continent_name": "Asia",
    "continent_keywords": "Asian airports",
    "has_metar": "VGHS",
    "has_taf": "VGHS",
    "world_rank": "590",
    "continent_rank": "177",
    "country_rank": "2",
    "region_rank": "1"
  },
  {
    "contentType": "airport",
    "datatype": "airport",
    "id": "26525",
    "ident": "VGBR",
    "type": "medium_airport",
    "name": "Barisal Airport",
    "regionRef": "306743",
    "continentRef": "302551",
    "municipality": "Barisal",
    "latitude_deg": "22.801000595092773",
    "longitude_deg": "90.30120086669922",
    "elevation_ft": "23",
    "magnetic_variation_deg": "-0.349",
    "icao_code": "VGBR",
    "iata_code": "BZL",
    "gps_code": "VGBR",
    "local_code": null,
    "has_scheduled_service": "1",
    "score": "750",
    "home_link": null,
    "wikipedia_link": "https://en.wikipedia.org/wiki/Barisal_Airport",
    "pilot_link": null,
    "keywords": null,
    "zoom": "13",
    "changeMemberRef": "80955",
    "changeDate": "2009-06-26 07:39:05",
    "changeType": "update",
    "changeComment": "",
    "airportRef": "26525",
    "visitor_count": "4",
    "comment_count": "1",
    "home_count": "0",
    "region_code": "BD-1",
    "region_name": "Barisal Division",
    "region_local_code": "1",
    "region_keywords": "Barisal bibhag",
    "countryRef": "302622",
    "country_code": "BD",
    "country_name": "Bangladesh",
    "country_keywords": "Bangladeshi airports",
    "continent_code": "AS",
    "continent_name": "Asia",
    "continent_keywords": "Asian airports",
    "has_metar": null,
    "has_taf": null,
    "world_rank": "3364",
    "continent_rank": "672",
    "country_rank": "4",
    "region_rank": "1"
  },
  {
    "contentType": "airport",
    "datatype": "airport",
    "id": "26526",
    "ident": "VGCB",
    "type": "medium_airport",
    "name": "Cox's Bazar Airport",
    "regionRef": "306744",
    "continentRef": "302551",
    "municipality": "Cox's Bazar",
    "latitude_deg": "21.452199935913086",
    "longitude_deg": "91.96389770507812",
    "elevation_ft": "12",
    "magnetic_variation_deg": "-0.414",
    "icao_code": "VGCB",
    "iata_code": "CXB",
    "gps_code": "VGCB",
    "local_code": null,
    "has_scheduled_service": "1",
    "score": "750",
    "home_link": null,
    "wikipedia_link": "https://en.wikipedia.org/wiki/Cox's_Bazar_Airport",
    "pilot_link": null,
    "keywords": null,
    "zoom": "13",
    "changeMemberRef": "80955",
    "changeDate": "2009-06-26 07:41:09",
    "changeType": "update",
    "changeComment": "",
    "airportRef": "26526",
    "visitor_count": "5",
    "comment_count": "0",
    "home_count": "0",
    "region_code": "BD-2",
    "region_name": "Chittagong Division",
    "region_local_code": "2",
    "region_keywords": "Chittagong bibhag",
    "countryRef": "302622",
    "country_code": "BD",
    "country_name": "Bangladesh",
    "country_keywords": "Bangladeshi airports",
    "continent_code": "AS",
    "continent_name": "Asia",
    "continent_keywords": "Asian airports",
    "has_metar": null,
    "has_taf": null,
    "world_rank": "3363",
    "continent_rank": "673",
    "country_rank": "5",
    "region_rank": "1"
  },
  {
    "contentType": "airport",
    "datatype": "airport",
    "id": "26527",
    "ident": "VGEG",
    "type": "medium_airport",
    "name": "Shah Amanat International Airport",
    "regionRef": "306744",
    "continentRef": "302551",
    "municipality": "Chattogram (Chittagong)",
    "latitude_deg": "22.249599",
    "longitude_deg": "91.813301",
    "elevation_ft": "12",
    "magnetic_variation_deg": "-0.386",
    "icao_code": "VGEG",
    "iata_code": "CGP",
    "gps_code": "VGEG",
    "local_code": null,
    "has_scheduled_service": "1",
    "score": "750",
    "home_link": null,
    "wikipedia_link": "https://en.wikipedia.org/wiki/Shah_Amanat_International_Airport",
    "pilot_link": null,
    "keywords": "M.A. Hannan International Airport",
    "zoom": "13",
    "changeMemberRef": "334409",
    "changeDate": "2021-01-21 17:16:24",
    "changeType": "update",
    "changeComment": null,
    "airportRef": "26527",
    "visitor_count": "7",
    "comment_count": "2",
    "home_count": "1",
    "region_code": "BD-2",
    "region_name": "Chittagong Division",
    "region_local_code": "2",
    "region_keywords": "Chittagong bibhag",
    "countryRef": "302622",
    "country_code": "BD",
    "country_name": "Bangladesh",
    "country_keywords": "Bangladeshi airports",
    "continent_code": "AS",
    "continent_name": "Asia",
    "continent_keywords": "Asian airports",
    "has_metar": "VGEG",
    "has_taf": "VGEG",
    "world_rank": "591",
    "continent_rank": "176",
    "country_rank": "1",
    "region_rank": "1"
  },
  {
    "contentType": "airport",
    "datatype": "airport",
    "id": "26529",
    "ident": "VGJR",
    "type": "medium_airport",
    "name": "Jessore Airport",
    "regionRef": "306741",
    "continentRef": "302551",
    "municipality": "Jashore (Jessore)",
    "latitude_deg": "23.1838",
    "longitude_deg": "89.160797",
    "elevation_ft": "20",
    "magnetic_variation_deg": "-0.318",
    "icao_code": "VGJR",
    "iata_code": "JSR",
    "gps_code": "VGJR",
    "local_code": null,
    "has_scheduled_service": "1",
    "score": "750",
    "home_link": null,
    "wikipedia_link": "https://en.wikipedia.org/wiki/Jessore_Airport",
    "pilot_link": null,
    "keywords": null,
    "zoom": "14",
    "changeMemberRef": "334409",
    "changeDate": "2021-10-15 17:28:16",
    "changeType": "update",
    "changeComment": null,
    "airportRef": "26529",
    "visitor_count": "2",
    "comment_count": "0",
    "home_count": "0",
    "region_code": "BD-4",
    "region_name": "Khulna Division",
    "region_local_code": "4",
    "region_keywords": "Khulna bibhag",
    "countryRef": "302622",
    "country_code": "BD",
    "country_name": "Bangladesh",
    "country_keywords": "Bangladeshi airports",
    "continent_code": "AS",
    "continent_name": "Asia",
    "continent_keywords": "Asian airports",
    "has_metar": null,
    "has_taf": null,
    "world_rank": "3361",
    "continent_rank": "675",
    "country_rank": "7",
    "region_rank": "1"
  },
  {
    "contentType": "airport",
    "datatype": "airport",
    "id": "26530",
    "ident": "VGRJ",
    "type": "medium_airport",
    "name": "Shah Mokhdum Airport",
    "regionRef": "306740",
    "continentRef": "302551",
    "municipality": "Rajshahi",
    "latitude_deg": "24.43720054626465",
    "longitude_deg": "88.61650085449219",
    "elevation_ft": "64",
    "magnetic_variation_deg": "-0.243",
    "icao_code": "VGRJ",
    "iata_code": "RJH",
    "gps_code": "VGRJ",
    "local_code": null,
    "has_scheduled_service": "1",
    "score": "750",
    "home_link": null,
    "wikipedia_link": "https://en.wikipedia.org/wiki/Shah_Makhdum_Airport",
    "pilot_link": null,
    "keywords": null,
    "zoom": "13",
    "changeMemberRef": "80955",
    "changeDate": "2009-06-26 07:45:13",
    "changeType": "update",
    "changeComment": "",
    "airportRef": "26530",
    "visitor_count": "2",
    "comment_count": "1",
    "home_count": "1",
    "region_code": "BD-5",
    "region_name": "Rajshahi Division",
    "region_local_code": "5",
    "region_keywords": "Rajshahi bibhag",
    "countryRef": "302622",
    "country_code": "BD",
    "country_name": "Bangladesh",
    "country_keywords": "Bangladeshi airports",
    "continent_code": "AS",
    "continent_name": "Asia",
    "continent_keywords": "Asian airports",
    "has_metar": null,
    "has_taf": null,
    "world_rank": "3360",
    "continent_rank": "676",
    "country_rank": "8",
    "region_rank": "1"
  },
  {
    "contentType": "airport",
    "datatype": "airport",
    "id": "26531",
    "ident": "VGSD",
    "type": "medium_airport",
    "name": "Saidpur Airport",
    "regionRef": "306740",
    "continentRef": "302551",
    "municipality": "Saidpur",
    "latitude_deg": "25.759199142456055",
    "longitude_deg": "88.90889739990234",
    "elevation_ft": "125",
    "magnetic_variation_deg": "-0.173",
    "icao_code": "VGSD",
    "iata_code": "SPD",
    "gps_code": "VGSD",
    "local_code": null,
    "has_scheduled_service": "1",
    "score": "750",
    "home_link": null,
    "wikipedia_link": "https://en.wikipedia.org/wiki/Saidpur_Airport",
    "pilot_link": null,
    "keywords": null,
    "zoom": "13",
    "changeMemberRef": "80955",
    "changeDate": "2009-06-26 07:44:14",
    "changeType": "update",
    "changeComment": "",
    "airportRef": "26531",
    "visitor_count": "2",
    "comment_count": "2",
    "home_count": "0",
    "region_code": "BD-5",
    "region_name": "Rajshahi Division",
    "region_local_code": "5",
    "region_keywords": "Rajshahi bibhag",
    "countryRef": "302622",
    "country_code": "BD",
    "country_name": "Bangladesh",
    "country_keywords": "Bangladeshi airports",
    "continent_code": "AS",
    "continent_name": "Asia",
    "continent_keywords": "Asian airports",
    "has_metar": null,
    "has_taf": null,
    "world_rank": "3359",
    "continent_rank": "677",
    "country_rank": "9",
    "region_rank": "1"
  },
  {
    "contentType": "airport",
    "datatype": "airport",
    "id": "26532",
    "ident": "VGSY",
    "type": "medium_airport",
    "name": "Osmany International Airport",
    "regionRef": "306739",
    "continentRef": "302551",
    "municipality": "Sylhet",
    "latitude_deg": "24.963832",
    "longitude_deg": "91.864843",
    "elevation_ft": "50",
    "magnetic_variation_deg": "-0.286",
    "icao_code": "VGSY",
    "iata_code": "ZYL",
    "gps_code": "VGSY",
    "local_code": null,
    "has_scheduled_service": "1",
    "score": "750",
    "home_link": null,
    "wikipedia_link": "https://en.wikipedia.org/wiki/Osmani_International_Airport",
    "pilot_link": null,
    "keywords": null,
    "zoom": "14",
    "changeMemberRef": "334409",
    "changeDate": "2021-10-29 15:08:29",
    "changeType": "update",
    "changeComment": null,
    "airportRef": "26532",
    "visitor_count": "3",
    "comment_count": "0",
    "home_count": "0",
    "region_code": "BD-6",
    "region_name": "Sylhet Division",
    "region_local_code": "6",
    "region_keywords": "Sylhet bibhag",
    "countryRef": "302622",
    "country_code": "BD",
    "country_name": "Bangladesh",
    "country_keywords": "Bangladeshi airports",
    "continent_code": "AS",
    "continent_name": "Asia",
    "continent_keywords": "Asian airports",
    "has_metar": null,
    "has_taf": null,
    "world_rank": "1510",
    "continent_rank": "300",
    "country_rank": "3",
    "region_rank": "1"
  },
  {
    "contentType": "airport",
    "datatype": "airport",
    "id": "26528",
    "ident": "VGIS",
    "type": "medium_airport",
    "name": "Ishurdi Airport",
    "regionRef": "306740",
    "continentRef": "302551",
    "municipality": "Ishurdi",
    "latitude_deg": "24.1525",
    "longitude_deg": "89.0494",
    "elevation_ft": "45",
    "magnetic_variation_deg": "-0.266",
    "icao_code": "VGIS",
    "iata_code": "IRD",
    "gps_code": "VGIS",
    "local_code": null,
    "has_scheduled_service": "0",
    "score": "250",
    "home_link": null,
    "wikipedia_link": "https://en.wikipedia.org/wiki/Ishwardi_Airport",
    "pilot_link": null,
    "keywords": null,
    "zoom": "13",
    "changeMemberRef": "524349",
    "changeDate": "2024-05-17 08:35:07",
    "changeType": "update",
    "changeComment": "wikipedia link added",
    "airportRef": "26528",
    "visitor_count": "1",
    "comment_count": "0",
    "home_count": "0",
    "region_code": "BD-5",
    "region_name": "Rajshahi Division",
    "region_local_code": "5",
    "region_keywords": "Rajshahi bibhag",
    "countryRef": "302622",
    "country_code": "BD",
    "country_name": "Bangladesh",
    "country_keywords": "Bangladeshi airports",
    "continent_code": "AS",
    "continent_name": "Asia",
    "continent_keywords": "Asian airports",
    "has_metar": null,
    "has_taf": null,
    "world_rank": "3362",
    "continent_rank": "674",
    "country_rank": "6",
    "region_rank": "1"
  },
  {
    "contentType": "airport",
    "datatype": "airport",
    "id": "26533",
    "ident": "VGTJ",
    "type": "small_airport",
    "name": "Tejgaon Airport",
    "regionRef": "306742",
    "continentRef": "302551",
    "municipality": "Dhaka",
    "latitude_deg": "23.778799057006836",
    "longitude_deg": "90.38269805908203",
    "elevation_ft": "24",
    "magnetic_variation_deg": "-0.306",
    "icao_code": null,
    "iata_code": null,
    "gps_code": "VGTJ",
    "local_code": null,
    "has_scheduled_service": "0",
    "score": "50",
    "home_link": null,
    "wikipedia_link": "https://en.wikipedia.org/wiki/Tejgaon_Airport",
    "pilot_link": null,
    "keywords": null,
    "zoom": "14",
    "changeMemberRef": "80955",
    "changeDate": "2009-06-26 07:50:09",
    "changeType": "update",
    "changeComment": "",
    "airportRef": "26533",
    "visitor_count": "1",
    "comment_count": "1",
    "home_count": "0",
    "region_code": "BD-3",
    "region_name": "Dhaka Division",
    "region_local_code": "3",
    "region_keywords": "Dhaka bibhag",
    "countryRef": "302622",
    "country_code": "BD",
    "country_name": "Bangladesh",
    "country_keywords": "Bangladeshi airports",
    "continent_code": "AS",
    "continent_name": "Asia",
    "continent_keywords": "Asian airports",
    "has_metar": null,
    "has_taf": null,
    "world_rank": "4602",
    "continent_rank": "993",
    "country_rank": "10",
    "region_rank": "1"
  },
  {
    "contentType": "airport",
    "datatype": "airport",
    "id": "32744",
    "ident": "VGSH",
    "type": "small_airport",
    "name": "Shamshernagar Airport",
    "regionRef": "306739",
    "continentRef": "302551",
    "municipality": "Shamshernagar",
    "latitude_deg": "24.398333",
    "longitude_deg": "91.916944",
    "elevation_ft": "56",
    "magnetic_variation_deg": null,
    "icao_code": "VGSH",
    "iata_code": "ZHM",
    "gps_code": "VGSH",
    "local_code": null,
    "has_scheduled_service": "0",
    "score": "50",
    "home_link": null,
    "wikipedia_link": "https://en.wikipedia.org/wiki/Shamshernagar_STOLport",
    "pilot_link": "http://www.caab.gov.bd/aip/aerodromes/vgsh.pdf",
    "keywords": null,
    "zoom": "14",
    "changeMemberRef": "83281",
    "changeDate": "2021-08-23 22:53:53",
    "changeType": "update",
    "changeComment": "Moved marker 4km ESE to runway. Added pilot info link.",
    "airportRef": "32744",
    "visitor_count": "1",
    "comment_count": "0",
    "home_count": "0",
    "region_code": "BD-6",
    "region_name": "Sylhet Division",
    "region_local_code": "6",
    "region_keywords": "Sylhet bibhag",
    "countryRef": "302622",
    "country_code": "BD",
    "country_name": "Bangladesh",
    "country_keywords": "Bangladeshi airports",
    "continent_code": "AS",
    "continent_name": "Asia",
    "continent_keywords": "Asian airports",
    "has_metar": null,
    "has_taf": null,
    "world_rank": null,
    "continent_rank": null,
    "country_rank": null,
    "region_rank": null
  },
  {
    "contentType": "airport",
    "datatype": "airport",
    "id": "340000",
    "ident": "BD-0019",
    "type": "small_airport",
    "name": "Noakhali Airport",
    "regionRef": "306744",
    "continentRef": "302551",
    "municipality": "Noakhali",
    "latitude_deg": "22.7389",
    "longitude_deg": "91.06489",
    "elevation_ft": "26",
    "magnetic_variation_deg": null,
    "icao_code": null,
    "iata_code": null,
    "gps_code": null,
    "local_code": null,
    "has_scheduled_service": "0",
    "score": "50",
    "home_link": null,
    "wikipedia_link": null,
    "pilot_link": null,
    "keywords": null,
    "zoom": "16",
    "changeMemberRef": "334409",
    "changeDate": "2021-10-29 15:17:24",
    "changeType": "update",
    "changeComment": null,
    "airportRef": "340000",
    "visitor_count": "1",
    "comment_count": "0",
    "home_count": "0",
    "region_code": "BD-2",
    "region_name": "Chittagong Division",
    "region_local_code": "2",
    "region_keywords": "Chittagong bibhag",
    "countryRef": "302622",
    "country_code": "BD",
    "country_name": "Bangladesh",
    "country_keywords": "Bangladeshi airports",
    "continent_code": "AS",
    "continent_name": "Asia",
    "continent_keywords": "Asian airports",
    "has_metar": null,
    "has_taf": null,
    "world_rank": null,
    "continent_rank": null,
    "country_rank": null,
    "region_rank": null
  },
  {
    "contentType": "airport",
    "datatype": "airport",
    "id": "32455",
    "ident": "VGSG",
    "type": "small_airport",
    "name": "Thakurgaon Airport",
    "regionRef": "306740",
    "continentRef": "302551",
    "municipality": "Thakurgaon",
    "latitude_deg": "26.016399",
    "longitude_deg": "88.403603",
    "elevation_ft": "176",
    "magnetic_variation_deg": null,
    "icao_code": "VGSG",
    "iata_code": "TKR",
    "gps_code": "VGSG",
    "local_code": null,
    "has_scheduled_service": "0",
    "score": "50",
    "home_link": null,
    "wikipedia_link": "https://en.wikipedia.org/wiki/Thakurgaon_Airport",
    "pilot_link": null,
    "keywords": null,
    "zoom": "14",
    "changeMemberRef": "524349",
    "changeDate": "2024-05-17 08:35:35",
    "changeType": "update",
    "changeComment": "wikipedia link added",
    "airportRef": "32455",
    "visitor_count": "0",
    "comment_count": "1",
    "home_count": "0",
    "region_code": "BD-5",
    "region_name": "Rajshahi Division",
    "region_local_code": "5",
    "region_keywords": "Rajshahi bibhag",
    "countryRef": "302622",
    "country_code": "BD",
    "country_name": "Bangladesh",
    "country_keywords": "Bangladeshi airports",
    "continent_code": "AS",
    "continent_name": "Asia",
    "continent_keywords": "Asian airports",
    "has_metar": null,
    "has_taf": null,
    "world_rank": null,
    "continent_rank": null,
    "country_rank": null,
    "region_rank": null
  },
  {
    "contentType": "airport",
    "datatype": "airport",
    "id": "31831",
    "ident": "VGLM",
    "type": "small_airport",
    "name": "Lalmonirhat Airport",
    "regionRef": "306740",
    "continentRef": "302551",
    "municipality": "Lalmonirhat",
    "latitude_deg": "25.887624",
    "longitude_deg": "89.431254",
    "elevation_ft": "106",
    "magnetic_variation_deg": null,
    "icao_code": null,
    "iata_code": null,
    "gps_code": "VGLM",
    "local_code": null,
    "has_scheduled_service": "0",
    "score": "50",
    "home_link": null,
    "wikipedia_link": "https://en.wikipedia.org/wiki/Lalmonirhat_Airport",
    "pilot_link": null,
    "keywords": null,
    "zoom": "14",
    "changeMemberRef": "83281",
    "changeDate": "2021-05-12 01:12:34",
    "changeType": "update",
    "changeComment": "Deleted IATA identifier, LLJ is: Silampari Airport, Indonesia. Added Wikipedia link.",
    "airportRef": "31831",
    "visitor_count": "0",
    "comment_count": "0",
    "home_count": "0",
    "region_code": "BD-5",
    "region_name": "Rajshahi Division",
    "region_local_code": "5",
    "region_keywords": "Rajshahi bibhag",
    "countryRef": "302622",
    "country_code": "BD",
    "country_name": "Bangladesh",
    "country_keywords": "Bangladeshi airports",
    "continent_code": "AS",
    "continent_name": "Asia",
    "continent_keywords": "Asian airports",
    "has_metar": null,
    "has_taf": null,
    "world_rank": null,
    "continent_rank": null,
    "country_rank": null,
    "region_rank": null
  },
  {
    "contentType": "airport",
    "datatype": "airport",
    "id": "309876",
    "ident": "VGBG",
    "type": "small_airport",
    "name": "Bogra Airport",
    "regionRef": "306740",
    "continentRef": "302551",
    "municipality": "Bogra",
    "latitude_deg": "24.8668",
    "longitude_deg": "89.3165",
    "elevation_ft": "69",
    "magnetic_variation_deg": null,
    "icao_code": null,
    "iata_code": null,
    "gps_code": "VGBG",
    "local_code": null,
    "has_scheduled_service": "0",
    "score": "50",
    "home_link": null,
    "wikipedia_link": "https://en.wikipedia.org/wiki/Bogra_STOLport",
    "pilot_link": null,
    "keywords": null,
    "zoom": "14",
    "changeMemberRef": "80959",
    "changeDate": "2014-07-23 16:07:58",
    "changeType": "update",
    "changeComment": null,
    "airportRef": "309876",
    "visitor_count": "1",
    "comment_count": "1",
    "home_count": "0",
    "region_code": "BD-5",
    "region_name": "Rajshahi Division",
    "region_local_code": "5",
    "region_keywords": "Rajshahi bibhag",
    "countryRef": "302622",
    "country_code": "BD",
    "country_name": "Bangladesh",
    "country_keywords": "Bangladeshi airports",
    "continent_code": "AS",
    "continent_name": "Asia",
    "continent_keywords": "Asian airports",
    "has_metar": null,
    "has_taf": null,
    "world_rank": null,
    "continent_rank": null,
    "country_rank": null,
    "region_rank": null
  },
  {
    "contentType": "airport",
    "datatype": "airport",
    "id": "30832",
    "ident": "VGCM",
    "type": "small_airport",
    "name": "Comilla Airport",
    "regionRef": "306744",
    "continentRef": "302551",
    "municipality": "Comilla",
    "latitude_deg": "23.437201",
    "longitude_deg": "91.189697",
    "elevation_ft": "25",
    "magnetic_variation_deg": null,
    "icao_code": "VGCM",
    "iata_code": "CLA",
    "gps_code": "VGCM",
    "local_code": null,
    "has_scheduled_service": "0",
    "score": "50",
    "home_link": null,
    "wikipedia_link": "https://en.wikipedia.org/wiki/Comilla_Airport",
    "pilot_link": null,
    "keywords": null,
    "zoom": "14",
    "changeMemberRef": "524349",
    "changeDate": "2024-05-17 08:34:42",
    "changeType": "update",
    "changeComment": "wikipedia link added",
    "airportRef": "30832",
    "visitor_count": "2",
    "comment_count": "0",
    "home_count": "0",
    "region_code": "BD-2",
    "region_name": "Chittagong Division",
    "region_local_code": "2",
    "region_keywords": "Chittagong bibhag",
    "countryRef": "302622",
    "country_code": "BD",
    "country_name": "Bangladesh",
    "country_keywords": "Bangladeshi airports",
    "continent_code": "AS",
    "continent_name": "Asia",
    "continent_keywords": "Asian airports",
    "has_metar": null,
    "has_taf": null,
    "world_rank": null,
    "continent_rank": null,
    "country_rank": null,
    "region_rank": null
  },
  {
    "contentType": "airport",
    "datatype": "airport",
    "id": "340003",
    "ident": "BD-0022",
    "type": "small_airport",
    "name": "Patuakhali Airport",
    "regionRef": "306743",
    "continentRef": "302551",
    "municipality": "Patuakhali",
    "latitude_deg": "22.37647",
    "longitude_deg": "90.32213",
    "elevation_ft": null,
    "magnetic_variation_deg": null,
    "icao_code": null,
    "iata_code": null,
    "gps_code": null,
    "local_code": null,
    "has_scheduled_service": "0",
    "score": "50",
    "home_link": null,
    "wikipedia_link": null,
    "pilot_link": null,
    "keywords": null,
    "zoom": "14",
    "changeMemberRef": "334409",
    "changeDate": "2021-01-21 17:32:29",
    "changeType": "create",
    "changeComment": null,
    "airportRef": "340003",
    "visitor_count": "1",
    "comment_count": "0",
    "home_count": "0",
    "region_code": "BD-1",
    "region_name": "Barisal Division",
    "region_local_code": "1",
    "region_keywords": "Barisal bibhag",
    "countryRef": "302622",
    "country_code": "BD",
    "country_name": "Bangladesh",
    "country_keywords": "Bangladeshi airports",
    "continent_code": "AS",
    "continent_name": "Asia",
    "continent_keywords": "Asian airports",
    "has_metar": null,
    "has_taf": null,
    "world_rank": null,
    "continent_rank": null,
    "country_rank": null,
    "region_rank": null
  },
  {
    "contentType": "airport",
    "datatype": "airport",
    "id": "349324",
    "ident": "BD-0030",
    "type": "heliport",
    "name": "Bolipara Heliport",
    "regionRef": "306744",
    "continentRef": "302551",
    "municipality": "Bolipara",
    "latitude_deg": "21.88065",
    "longitude_deg": "92.39703",
    "elevation_ft": "434",
    "magnetic_variation_deg": null,
    "icao_code": null,
    "iata_code": null,
    "gps_code": null,
    "local_code": null,
    "has_scheduled_service": "0",
    "score": "0",
    "home_link": null,
    "wikipedia_link": null,
    "pilot_link": null,
    "keywords": null,
    "zoom": "17",
    "changeMemberRef": "334409",
    "changeDate": "2021-10-29 15:46:40",
    "changeType": "create",
    "changeComment": null,
    "airportRef": "349324",
    "visitor_count": "0",
    "comment_count": "0",
    "home_count": "0",
    "region_code": "BD-2",
    "region_name": "Chittagong Division",
    "region_local_code": "2",
    "region_keywords": "Chittagong bibhag",
    "countryRef": "302622",
    "country_code": "BD",
    "country_name": "Bangladesh",
    "country_keywords": "Bangladeshi airports",
    "continent_code": "AS",
    "continent_name": "Asia",
    "continent_keywords": "Asian airports",
    "has_metar": null,
    "has_taf": null,
    "world_rank": null,
    "continent_rank": null,
    "country_rank": null,
    "region_rank": null
  },
  {
    "contentType": "airport",
    "datatype": "airport",
    "id": "349325",
    "ident": "BD-0031",
    "type": "heliport",
    "name": "Keokradong Heliport",
    "regionRef": "306744",
    "continentRef": "302551",
    "municipality": "Keokradong",
    "latitude_deg": "21.94874",
    "longitude_deg": "92.5146",
    "elevation_ft": "3186",
    "magnetic_variation_deg": null,
    "icao_code": null,
    "iata_code": null,
    "gps_code": null,
    "local_code": null,
    "has_scheduled_service": "0",
    "score": "0",
    "home_link": null,
    "wikipedia_link": null,
    "pilot_link": null,
    "keywords": null,
    "zoom": "17",
    "changeMemberRef": "334409",
    "changeDate": "2021-10-29 15:47:28",
    "changeType": "create",
    "changeComment": null,
    "airportRef": "349325",
    "visitor_count": "0",
    "comment_count": "0",
    "home_count": "0",
    "region_code": "BD-2",
    "region_name": "Chittagong Division",
    "region_local_code": "2",
    "region_keywords": "Chittagong bibhag",
    "countryRef": "302622",
    "country_code": "BD",
    "country_name": "Bangladesh",
    "country_keywords": "Bangladeshi airports",
    "continent_code": "AS",
    "continent_name": "Asia",
    "continent_keywords": "Asian airports",
    "has_metar": null,
    "has_taf": null,
    "world_rank": null,
    "continent_rank": null,
    "country_rank": null,
    "region_rank": null
  },
  {
    "contentType": "airport",
    "datatype": "airport",
    "id": "349320",
    "ident": "BD-0026",
    "type": "heliport",
    "name": "Dhumdumia BGB Heliport",
    "regionRef": "306744",
    "continentRef": "302551",
    "municipality": "Dhumdumia",
    "latitude_deg": "20.95911",
    "longitude_deg": "92.25133",
    "elevation_ft": "18",
    "magnetic_variation_deg": null,
    "icao_code": null,
    "iata_code": null,
    "gps_code": null,
    "local_code": null,
    "has_scheduled_service": "0",
    "score": "0",
    "home_link": null,
    "wikipedia_link": null,
    "pilot_link": null,
    "keywords": null,
    "zoom": "17",
    "changeMemberRef": "334409",
    "changeDate": "2021-10-29 15:43:03",
    "changeType": "update",
    "changeComment": null,
    "airportRef": "349320",
    "visitor_count": "0",
    "comment_count": "0",
    "home_count": "0",
    "region_code": "BD-2",
    "region_name": "Chittagong Division",
    "region_local_code": "2",
    "region_keywords": "Chittagong bibhag",
    "countryRef": "302622",
    "country_code": "BD",
    "country_name": "Bangladesh",
    "country_keywords": "Bangladeshi airports",
    "continent_code": "AS",
    "continent_name": "Asia",
    "continent_keywords": "Asian airports",
    "has_metar": null,
    "has_taf": null,
    "world_rank": null,
    "continent_rank": null,
    "country_rank": null,
    "region_rank": null
  },
  {
    "contentType": "airport",
    "datatype": "airport",
    "id": "349326",
    "ident": "BD-0032",
    "type": "heliport",
    "name": "Thanchi BGB Heliport",
    "regionRef": "306744",
    "continentRef": "302551",
    "municipality": "Thanchi",
    "latitude_deg": "21.81823",
    "longitude_deg": "92.44067",
    "elevation_ft": "233",
    "magnetic_variation_deg": null,
    "icao_code": null,
    "iata_code": null,
    "gps_code": null,
    "local_code": null,
    "has_scheduled_service": "0",
    "score": "0",
    "home_link": null,
    "wikipedia_link": null,
    "pilot_link": null,
    "keywords": null,
    "zoom": "17",
    "changeMemberRef": "334409",
    "changeDate": "2021-10-29 15:49:03",
    "changeType": "create",
    "changeComment": null,
    "airportRef": "349326",
    "visitor_count": "0",
    "comment_count": "0",
    "home_count": "0",
    "region_code": "BD-2",
    "region_name": "Chittagong Division",
    "region_local_code": "2",
    "region_keywords": "Chittagong bibhag",
    "countryRef": "302622",
    "country_code": "BD",
    "country_name": "Bangladesh",
    "country_keywords": "Bangladeshi airports",
    "continent_code": "AS",
    "continent_name": "Asia",
    "continent_keywords": "Asian airports",
    "has_metar": null,
    "has_taf": null,
    "world_rank": null,
    "continent_rank": null,
    "country_rank": null,
    "region_rank": null
  },
  {
    "contentType": "airport",
    "datatype": "airport",
    "id": "349327",
    "ident": "BD-0033",
    "type": "heliport",
    "name": "Remakri Heliport",
    "regionRef": "306744",
    "continentRef": "302551",
    "municipality": "Remakri",
    "latitude_deg": "21.67607",
    "longitude_deg": "92.52014",
    "elevation_ft": "233",
    "magnetic_variation_deg": null,
    "icao_code": null,
    "iata_code": null,
    "gps_code": null,
    "local_code": null,
    "has_scheduled_service": "0",
    "score": "0",
    "home_link": null,
    "wikipedia_link": null,
    "pilot_link": null,
    "keywords": null,
    "zoom": "17",
    "changeMemberRef": "334409",
    "changeDate": "2021-10-29 15:50:41",
    "changeType": "create",
    "changeComment": null,
    "airportRef": "349327",
    "visitor_count": "0",
    "comment_count": "0",
    "home_count": "0",
    "region_code": "BD-2",
    "region_name": "Chittagong Division",
    "region_local_code": "2",
    "region_keywords": "Chittagong bibhag",
    "countryRef": "302622",
    "country_code": "BD",
    "country_name": "Bangladesh",
    "country_keywords": "Bangladeshi airports",
    "continent_code": "AS",
    "continent_name": "Asia",
    "continent_keywords": "Asian airports",
    "has_metar": null,
    "has_taf": null,
    "world_rank": null,
    "continent_rank": null,
    "country_rank": null,
    "region_rank": null
  },
  {
    "contentType": "airport",
    "datatype": "airport",
    "id": "349328",
    "ident": "BD-0034",
    "type": "heliport",
    "name": "Boro Mowdak Heliport",
    "regionRef": "306744",
    "continentRef": "302551",
    "municipality": "Boro Mowdak",
    "latitude_deg": "21.57058",
    "longitude_deg": "92.57103",
    "elevation_ft": "341",
    "magnetic_variation_deg": null,
    "icao_code": null,
    "iata_code": null,
    "gps_code": null,
    "local_code": null,
    "has_scheduled_service": "0",
    "score": "0",
    "home_link": null,
    "wikipedia_link": null,
    "pilot_link": null,
    "keywords": null,
    "zoom": "17",
    "changeMemberRef": "334409",
    "changeDate": "2021-10-29 15:51:49",
    "changeType": "create",
    "changeComment": null,
    "airportRef": "349328",
    "visitor_count": "0",
    "comment_count": "0",
    "home_count": "0",
    "region_code": "BD-2",
    "region_name": "Chittagong Division",
    "region_local_code": "2",
    "region_keywords": "Chittagong bibhag",
    "countryRef": "302622",
    "country_code": "BD",
    "country_name": "Bangladesh",
    "country_keywords": "Bangladeshi airports",
    "continent_code": "AS",
    "continent_name": "Asia",
    "continent_keywords": "Asian airports",
    "has_metar": null,
    "has_taf": null,
    "world_rank": null,
    "continent_rank": null,
    "country_rank": null,
    "region_rank": null
  },
  {
    "contentType": "airport",
    "datatype": "airport",
    "id": "349329",
    "ident": "BD-0035",
    "type": "heliport",
    "name": "Upper Sangu River Heliport 1",
    "regionRef": "306744",
    "continentRef": "302551",
    "municipality": "Remakri",
    "latitude_deg": "21.40321",
    "longitude_deg": "92.58095",
    "elevation_ft": "502",
    "magnetic_variation_deg": null,
    "icao_code": null,
    "iata_code": null,
    "gps_code": null,
    "local_code": null,
    "has_scheduled_service": "0",
    "score": "0",
    "home_link": null,
    "wikipedia_link": null,
    "pilot_link": null,
    "keywords": null,
    "zoom": "17",
    "changeMemberRef": "334409",
    "changeDate": "2021-10-29 16:02:52",
    "changeType": "update",
    "changeComment": null,
    "airportRef": "349329",
    "visitor_count": "0",
    "comment_count": "0",
    "home_count": "0",
    "region_code": "BD-2",
    "region_name": "Chittagong Division",
    "region_local_code": "2",
    "region_keywords": "Chittagong bibhag",
    "countryRef": "302622",
    "country_code": "BD",
    "country_name": "Bangladesh",
    "country_keywords": "Bangladeshi airports",
    "continent_code": "AS",
    "continent_name": "Asia",
    "continent_keywords": "Asian airports",
    "has_metar": null,
    "has_taf": null,
    "world_rank": null,
    "continent_rank": null,
    "country_rank": null,
    "region_rank": null
  },
  {
    "contentType": "airport",
    "datatype": "airport",
    "id": "349330",
    "ident": "BD-0036",
    "type": "heliport",
    "name": "Upper Sangu River Heliport 2",
    "regionRef": "306744",
    "continentRef": "302551",
    "municipality": "Remakri",
    "latitude_deg": "21.40229",
    "longitude_deg": "92.60747",
    "elevation_ft": "609",
    "magnetic_variation_deg": null,
    "icao_code": null,
    "iata_code": null,
    "gps_code": null,
    "local_code": null,
    "has_scheduled_service": "0",
    "score": "0",
    "home_link": null,
    "wikipedia_link": null,
    "pilot_link": null,
    "keywords": null,
    "zoom": "17",
    "changeMemberRef": "334409",
    "changeDate": "2021-10-29 16:03:02",
    "changeType": "update",
    "changeComment": null,
    "airportRef": "349330",
    "visitor_count": "0",
    "comment_count": "0",
    "home_count": "0",
    "region_code": "BD-2",
    "region_name": "Chittagong Division",
    "region_local_code": "2",
    "region_keywords": "Chittagong bibhag",
    "countryRef": "302622",
    "country_code": "BD",
    "country_name": "Bangladesh",
    "country_keywords": "Bangladeshi airports",
    "continent_code": "AS",
    "continent_name": "Asia",
    "continent_keywords": "Asian airports",
    "has_metar": null,
    "has_taf": null,
    "world_rank": null,
    "continent_rank": null,
    "country_rank": null,
    "region_rank": null
  },
  {
    "contentType": "airport",
    "datatype": "airport",
    "id": "349331",
    "ident": "BD-0037",
    "type": "heliport",
    "name": "Marang Chara Heliport",
    "regionRef": "306744",
    "continentRef": "302551",
    "municipality": "Remakri",
    "latitude_deg": "21.34993",
    "longitude_deg": "92.60561",
    "elevation_ft": "491",
    "magnetic_variation_deg": null,
    "icao_code": null,
    "iata_code": null,
    "gps_code": null,
    "local_code": null,
    "has_scheduled_service": "0",
    "score": "0",
    "home_link": null,
    "wikipedia_link": null,
    "pilot_link": null,
    "keywords": null,
    "zoom": "14",
    "changeMemberRef": "334409",
    "changeDate": "2021-10-29 16:02:04",
    "changeType": "create",
    "changeComment": null,
    "airportRef": "349331",
    "visitor_count": "0",
    "comment_count": "0",
    "home_count": "0",
    "region_code": "BD-2",
    "region_name": "Chittagong Division",
    "region_local_code": "2",
    "region_keywords": "Chittagong bibhag",
    "countryRef": "302622",
    "country_code": "BD",
    "country_name": "Bangladesh",
    "country_keywords": "Bangladeshi airports",
    "continent_code": "AS",
    "continent_name": "Asia",
    "continent_keywords": "Asian airports",
    "has_metar": null,
    "has_taf": null,
    "world_rank": null,
    "continent_rank": null,
    "country_rank": null,
    "region_rank": null
  },
  {
    "contentType": "airport",
    "datatype": "airport",
    "id": "349332",
    "ident": "BD-0038",
    "type": "heliport",
    "name": "Upper Sangu River Heliport 3",
    "regionRef": "306744",
    "continentRef": "302551",
    "municipality": "Remakri",
    "latitude_deg": "21.30249",
    "longitude_deg": "92.61998",
    "elevation_ft": "941",
    "magnetic_variation_deg": null,
    "icao_code": null,
    "iata_code": null,
    "gps_code": null,
    "local_code": null,
    "has_scheduled_service": "0",
    "score": "0",
    "home_link": null,
    "wikipedia_link": null,
    "pilot_link": null,
    "keywords": null,
    "zoom": "17",
    "changeMemberRef": "334409",
    "changeDate": "2021-10-29 16:04:56",
    "changeType": "create",
    "changeComment": null,
    "airportRef": "349332",
    "visitor_count": "0",
    "comment_count": "0",
    "home_count": "0",
    "region_code": "BD-2",
    "region_name": "Chittagong Division",
    "region_local_code": "2",
    "region_keywords": "Chittagong bibhag",
    "countryRef": "302622",
    "country_code": "BD",
    "country_name": "Bangladesh",
    "country_keywords": "Bangladeshi airports",
    "continent_code": "AS",
    "continent_name": "Asia",
    "continent_keywords": "Asian airports",
    "has_metar": null,
    "has_taf": null,
    "world_rank": null,
    "continent_rank": null,
    "country_rank": null,
    "region_rank": null
  },
  {
    "contentType": "airport",
    "datatype": "airport",
    "id": "595338",
    "ident": "BD-0043",
    "type": "heliport",
    "name": "Chapal Nawabganj Heliport",
    "regionRef": "306740",
    "continentRef": "302551",
    "municipality": "Nawabganj",
    "latitude_deg": "24.586668",
    "longitude_deg": "88.283111",
    "elevation_ft": "75",
    "magnetic_variation_deg": null,
    "icao_code": null,
    "iata_code": null,
    "gps_code": null,
    "local_code": null,
    "has_scheduled_service": "0",
    "score": "0",
    "home_link": null,
    "wikipedia_link": null,
    "pilot_link": null,
    "keywords": null,
    "zoom": "18",
    "changeMemberRef": "334409",
    "changeDate": "2025-03-17 10:43:27",
    "changeType": "create",
    "changeComment": null,
    "airportRef": "595338",
    "visitor_count": "0",
    "comment_count": "0",
    "home_count": "0",
    "region_code": "BD-5",
    "region_name": "Rajshahi Division",
    "region_local_code": "5",
    "region_keywords": "Rajshahi bibhag",
    "countryRef": "302622",
    "country_code": "BD",
    "country_name": "Bangladesh",
    "country_keywords": "Bangladeshi airports",
    "continent_code": "AS",
    "continent_name": "Asia",
    "continent_keywords": "Asian airports",
    "has_metar": null,
    "has_taf": null,
    "world_rank": null,
    "continent_rank": null,
    "country_rank": null,
    "region_rank": null
  },
  {
    "contentType": "airport",
    "datatype": "airport",
    "id": "349397",
    "ident": "BD-0039",
    "type": "closed",
    "name": "Bajitpur Regional Airport",
    "regionRef": "306742",
    "continentRef": "302551",
    "municipality": "Bajitpur",
    "latitude_deg": "24.21232",
    "longitude_deg": "90.9065",
    "elevation_ft": "33",
    "magnetic_variation_deg": null,
    "icao_code": null,
    "iata_code": null,
    "gps_code": null,
    "local_code": null,
    "has_scheduled_service": "0",
    "score": "0",
    "home_link": null,
    "wikipedia_link": null,
    "pilot_link": null,
    "keywords": null,
    "zoom": "15",
    "changeMemberRef": "334409",
    "changeDate": "2021-11-01 15:13:12",
    "changeType": "create",
    "changeComment": null,
    "airportRef": "349397",
    "visitor_count": "0",
    "comment_count": "0",
    "home_count": "0",
    "region_code": "BD-3",
    "region_name": "Dhaka Division",
    "region_local_code": "3",
    "region_keywords": "Dhaka bibhag",
    "countryRef": "302622",
    "country_code": "BD",
    "country_name": "Bangladesh",
    "country_keywords": "Bangladeshi airports",
    "continent_code": "AS",
    "continent_name": "Asia",
    "continent_keywords": "Asian airports",
    "has_metar": null,
    "has_taf": null,
    "world_rank": null,
    "continent_rank": null,
    "country_rank": null,
    "region_rank": null
  },
  {
    "contentType": "airport",
    "datatype": "airport",
    "id": "516839",
    "ident": "BD-0041",
    "type": "heliport",
    "name": "Uttara Helipad",
    "regionRef": "306742",
    "continentRef": "302551",
    "municipality": "Dhaka",
    "latitude_deg": "23.892722",
    "longitude_deg": "90.390378",
    "elevation_ft": "31",
    "magnetic_variation_deg": null,
    "icao_code": null,
    "iata_code": null,
    "gps_code": null,
    "local_code": null,
    "has_scheduled_service": "0",
    "score": "0",
    "home_link": null,
    "wikipedia_link": null,
    "pilot_link": "https://www.spottingmode.com/airfields/airport/46504",
    "keywords": null,
    "zoom": "17",
    "changeMemberRef": "83281",
    "changeDate": "2023-12-09 03:00:37",
    "changeType": "create",
    "changeComment": "New entry.",
    "airportRef": "516839",
    "visitor_count": "0",
    "comment_count": "0",
    "home_count": "0",
    "region_code": "BD-3",
    "region_name": "Dhaka Division",
    "region_local_code": "3",
    "region_keywords": "Dhaka bibhag",
    "countryRef": "302622",
    "country_code": "BD",
    "country_name": "Bangladesh",
    "country_keywords": "Bangladeshi airports",
    "continent_code": "AS",
    "continent_name": "Asia",
    "continent_keywords": "Asian airports",
    "has_metar": null,
    "has_taf": null,
    "world_rank": null,
    "continent_rank": null,
    "country_rank": null,
    "region_rank": null
  },
  {
    "contentType": "airport",
    "datatype": "airport",
    "id": "313421",
    "ident": "BD-0042",
    "type": "closed",
    "name": "Khan Jahan Ali Airport (under construction)",
    "regionRef": "306741",
    "continentRef": "302551",
    "municipality": "Bagerhat",
    "latitude_deg": "22.6486",
    "longitude_deg": "89.6454",
    "elevation_ft": "21",
    "magnetic_variation_deg": null,
    "icao_code": null,
    "iata_code": null,
    "gps_code": null,
    "local_code": null,
    "has_scheduled_service": "0",
    "score": "0",
    "home_link": null,
    "wikipedia_link": "https://en.wikipedia.org/wiki/Khan_Jahan_Ali_Airport",
    "pilot_link": null,
    "keywords": "Mongla, Bagerhat, KHL",
    "zoom": "14",
    "changeMemberRef": "504793",
    "changeDate": "2025-02-25 14:51:25",
    "changeType": "update",
    "changeComment": "Remove codes for closed airports.",
    "airportRef": "313421",
    "visitor_count": "0",
    "comment_count": "0",
    "home_count": "0",
    "region_code": "BD-4",
    "region_name": "Khulna Division",
    "region_local_code": "4",
    "region_keywords": "Khulna bibhag",
    "countryRef": "302622",
    "country_code": "BD",
    "country_name": "Bangladesh",
    "country_keywords": "Bangladeshi airports",
    "continent_code": "AS",
    "continent_name": "Asia",
    "continent_keywords": "Asian airports",
    "has_metar": null,
    "has_taf": null,
    "world_rank": null,
    "continent_rank": null,
    "country_rank": null,
    "region_rank": null
  },
  {
    "contentType": "airport",
    "datatype": "airport",
    "id": "516838",
    "ident": "BD-0040",
    "type": "heliport",
    "name": "Khulna Circuit House Helipad",
    "regionRef": "306741",
    "continentRef": "302551",
    "municipality": "Khulna",
    "latitude_deg": "22.813996",
    "longitude_deg": "89.569741",
    "elevation_ft": "22",
    "magnetic_variation_deg": null,
    "icao_code": null,
    "iata_code": null,
    "gps_code": null,
    "local_code": null,
    "has_scheduled_service": "0",
    "score": "0",
    "home_link": null,
    "wikipedia_link": null,
    "pilot_link": "https://www.spottingmode.com/airfields/airport/46503",
    "keywords": null,
    "zoom": "17",
    "changeMemberRef": "83281",
    "changeDate": "2023-12-09 02:40:04",
    "changeType": "create",
    "changeComment": "New entry.",
    "airportRef": "516838",
    "visitor_count": "0",
    "comment_count": "0",
    "home_count": "0",
    "region_code": "BD-4",
    "region_name": "Khulna Division",
    "region_local_code": "4",
    "region_keywords": "Khulna bibhag",
    "countryRef": "302622",
    "country_code": "BD",
    "country_name": "Bangladesh",
    "country_keywords": "Bangladeshi airports",
    "continent_code": "AS",
    "continent_name": "Asia",
    "continent_keywords": "Asian airports",
    "has_metar": null,
    "has_taf": null,
    "world_rank": null,
    "continent_rank": null,
    "country_rank": null,
    "region_rank": null
  },
  {
    "contentType": "airport",
    "datatype": "airport",
    "id": "339993",
    "ident": "BD-0012",
    "type": "heliport",
    "name": "Bhasan Char Nayamasti Heliport 2",
    "regionRef": "306744",
    "continentRef": "302551",
    "municipality": "Hatiya",
    "latitude_deg": "22.36626",
    "longitude_deg": "91.36998",
    "elevation_ft": null,
    "magnetic_variation_deg": null,
    "icao_code": null,
    "iata_code": null,
    "gps_code": null,
    "local_code": null,
    "has_scheduled_service": "0",
    "score": "0",
    "home_link": null,
    "wikipedia_link": null,
    "pilot_link": null,
    "keywords": null,
    "zoom": "14",
    "changeMemberRef": "334409",
    "changeDate": "2021-01-21 17:20:11",
    "changeType": "create",
    "changeComment": "This island is only 14 years old!",
    "airportRef": "339993",
    "visitor_count": "0",
    "comment_count": "0",
    "home_count": "0",
    "region_code": "BD-2",
    "region_name": "Chittagong Division",
    "region_local_code": "2",
    "region_keywords": "Chittagong bibhag",
    "countryRef": "302622",
    "country_code": "BD",
    "country_name": "Bangladesh",
    "country_keywords": "Bangladeshi airports",
    "continent_code": "AS",
    "continent_name": "Asia",
    "continent_keywords": "Asian airports",
    "has_metar": null,
    "has_taf": null,
    "world_rank": null,
    "continent_rank": null,
    "country_rank": null,
    "region_rank": null
  },
  {
    "contentType": "airport",
    "datatype": "airport",
    "id": "340002",
    "ident": "BD-0021",
    "type": "heliport",
    "name": "Burhanuddin Heliport",
    "regionRef": "306743",
    "continentRef": "302551",
    "municipality": "Burhanuddin",
    "latitude_deg": "22.508",
    "longitude_deg": "90.71304",
    "elevation_ft": null,
    "magnetic_variation_deg": null,
    "icao_code": null,
    "iata_code": null,
    "gps_code": null,
    "local_code": null,
    "has_scheduled_service": "0",
    "score": "0",
    "home_link": null,
    "wikipedia_link": null,
    "pilot_link": null,
    "keywords": null,
    "zoom": "14",
    "changeMemberRef": "334409",
    "changeDate": "2021-01-21 17:31:53",
    "changeType": "create",
    "changeComment": null,
    "airportRef": "340002",
    "visitor_count": "0",
    "comment_count": "0",
    "home_count": "0",
    "region_code": "BD-1",
    "region_name": "Barisal Division",
    "region_local_code": "1",
    "region_keywords": "Barisal bibhag",
    "countryRef": "302622",
    "country_code": "BD",
    "country_name": "Bangladesh",
    "country_keywords": "Bangladeshi airports",
    "continent_code": "AS",
    "continent_name": "Asia",
    "continent_keywords": "Asian airports",
    "has_metar": null,
    "has_taf": null,
    "world_rank": null,
    "continent_rank": null,
    "country_rank": null,
    "region_rank": null
  },
  {
    "contentType": "airport",
    "datatype": "airport",
    "id": "339981",
    "ident": "BD-0001",
    "type": "heliport",
    "name": "Inani Beach Heliport",
    "regionRef": "306744",
    "continentRef": "302551",
    "municipality": "Inani",
    "latitude_deg": "21.22472",
    "longitude_deg": "92.0482",
    "elevation_ft": null,
    "magnetic_variation_deg": null,
    "icao_code": null,
    "iata_code": null,
    "gps_code": null,
    "local_code": null,
    "has_scheduled_service": "0",
    "score": "0",
    "home_link": null,
    "wikipedia_link": null,
    "pilot_link": null,
    "keywords": null,
    "zoom": "14",
    "changeMemberRef": "334409",
    "changeDate": "2021-01-21 17:06:23",
    "changeType": "create",
    "changeComment": null,
    "airportRef": "339981",
    "visitor_count": "0",
    "comment_count": "0",
    "home_count": "0",
    "region_code": "BD-2",
    "region_name": "Chittagong Division",
    "region_local_code": "2",
    "region_keywords": "Chittagong bibhag",
    "countryRef": "302622",
    "country_code": "BD",
    "country_name": "Bangladesh",
    "country_keywords": "Bangladeshi airports",
    "continent_code": "AS",
    "continent_name": "Asia",
    "continent_keywords": "Asian airports",
    "has_metar": null,
    "has_taf": null,
    "world_rank": null,
    "continent_rank": null,
    "country_rank": null,
    "region_rank": null
  },
  {
    "contentType": "airport",
    "datatype": "airport",
    "id": "339982",
    "ident": "BD-0002",
    "type": "heliport",
    "name": "Ocean Paradise Heliport",
    "regionRef": "306744",
    "continentRef": "302551",
    "municipality": "Cox's Bazar",
    "latitude_deg": "21.418572",
    "longitude_deg": "91.982574",
    "elevation_ft": null,
    "magnetic_variation_deg": null,
    "icao_code": null,
    "iata_code": null,
    "gps_code": null,
    "local_code": null,
    "has_scheduled_service": "0",
    "score": "0",
    "home_link": null,
    "wikipedia_link": null,
    "pilot_link": null,
    "keywords": null,
    "zoom": "14",
    "changeMemberRef": "334409",
    "changeDate": "2021-01-21 17:08:40",
    "changeType": "create",
    "changeComment": null,
    "airportRef": "339982",
    "visitor_count": "0",
    "comment_count": "0",
    "home_count": "0",
    "region_code": "BD-2",
    "region_name": "Chittagong Division",
    "region_local_code": "2",
    "region_keywords": "Chittagong bibhag",
    "countryRef": "302622",
    "country_code": "BD",
    "country_name": "Bangladesh",
    "country_keywords": "Bangladeshi airports",
    "continent_code": "AS",
    "continent_name": "Asia",
    "continent_keywords": "Asian airports",
    "has_metar": null,
    "has_taf": null,
    "world_rank": null,
    "continent_rank": null,
    "country_rank": null,
    "region_rank": null
  },
  {
    "contentType": "airport",
    "datatype": "airport",
    "id": "339983",
    "ident": "BD-0003",
    "type": "closed",
    "name": "Hotel Sea Palace Heliport",
    "regionRef": "306744",
    "continentRef": "302551",
    "municipality": "Cox's Bazar",
    "latitude_deg": "21.419863",
    "longitude_deg": "91.981569",
    "elevation_ft": null,
    "magnetic_variation_deg": null,
    "icao_code": null,
    "iata_code": null,
    "gps_code": null,
    "local_code": null,
    "has_scheduled_service": "0",
    "score": "0",
    "home_link": null,
    "wikipedia_link": null,
    "pilot_link": null,
    "keywords": null,
    "zoom": "14",
    "changeMemberRef": "334409",
    "changeDate": "2021-01-21 17:09:08",
    "changeType": "create",
    "changeComment": null,
    "airportRef": "339983",
    "visitor_count": "0",
    "comment_count": "0",
    "home_count": "0",
    "region_code": "BD-2",
    "region_name": "Chittagong Division",
    "region_local_code": "2",
    "region_keywords": "Chittagong bibhag",
    "countryRef": "302622",
    "country_code": "BD",
    "country_name": "Bangladesh",
    "country_keywords": "Bangladeshi airports",
    "continent_code": "AS",
    "continent_name": "Asia",
    "continent_keywords": "Asian airports",
    "has_metar": null,
    "has_taf": null,
    "world_rank": null,
    "continent_rank": null,
    "country_rank": null,
    "region_rank": null
  },
  {
    "contentType": "airport",
    "datatype": "airport",
    "id": "339984",
    "ident": "BD-0004",
    "type": "heliport",
    "name": "Nilgiri Heliport",
    "regionRef": "306744",
    "continentRef": "302551",
    "municipality": "Barpara",
    "latitude_deg": "21.91355",
    "longitude_deg": "92.3244",
    "elevation_ft": null,
    "magnetic_variation_deg": null,
    "icao_code": null,
    "iata_code": null,
    "gps_code": null,
    "local_code": null,
    "has_scheduled_service": "0",
    "score": "0",
    "home_link": null,
    "wikipedia_link": null,
    "pilot_link": null,
    "keywords": null,
    "zoom": "14",
    "changeMemberRef": "334409",
    "changeDate": "2021-01-21 17:10:28",
    "changeType": "create",
    "changeComment": null,
    "airportRef": "339984",
    "visitor_count": "0",
    "comment_count": "0",
    "home_count": "0",
    "region_code": "BD-2",
    "region_name": "Chittagong Division",
    "region_local_code": "2",
    "region_keywords": "Chittagong bibhag",
    "countryRef": "302622",
    "country_code": "BD",
    "country_name": "Bangladesh",
    "country_keywords": "Bangladeshi airports",
    "continent_code": "AS",
    "continent_name": "Asia",
    "continent_keywords": "Asian airports",
    "has_metar": null,
    "has_taf": null,
    "world_rank": null,
    "continent_rank": null,
    "country_rank": null,
    "region_rank": null
  },
  {
    "contentType": "airport",
    "datatype": "airport",
    "id": "339985",
    "ident": "BD-0005",
    "type": "heliport",
    "name": "Boga Lake Heliport",
    "regionRef": "306744",
    "continentRef": "302551",
    "municipality": "Ruma",
    "latitude_deg": "21.97982",
    "longitude_deg": "92.46715",
    "elevation_ft": null,
    "magnetic_variation_deg": null,
    "icao_code": null,
    "iata_code": null,
    "gps_code": null,
    "local_code": null,
    "has_scheduled_service": "0",
    "score": "0",
    "home_link": null,
    "wikipedia_link": null,
    "pilot_link": null,
    "keywords": null,
    "zoom": "14",
    "changeMemberRef": "334409",
    "changeDate": "2021-01-21 17:11:26",
    "changeType": "create",
    "changeComment": null,
    "airportRef": "339985",
    "visitor_count": "0",
    "comment_count": "0",
    "home_count": "0",
    "region_code": "BD-2",
    "region_name": "Chittagong Division",
    "region_local_code": "2",
    "region_keywords": "Chittagong bibhag",
    "countryRef": "302622",
    "country_code": "BD",
    "country_name": "Bangladesh",
    "country_keywords": "Bangladeshi airports",
    "continent_code": "AS",
    "continent_name": "Asia",
    "continent_keywords": "Asian airports",
    "has_metar": null,
    "has_taf": null,
    "world_rank": null,
    "continent_rank": null,
    "country_rank": null,
    "region_rank": null
  },
  {
    "contentType": "airport",
    "datatype": "airport",
    "id": "339987",
    "ident": "BD-0006",
    "type": "heliport",
    "name": "Ruma Helipad",
    "regionRef": "306744",
    "continentRef": "302551",
    "municipality": "Ruma",
    "latitude_deg": "22.05122",
    "longitude_deg": "92.38641",
    "elevation_ft": null,
    "magnetic_variation_deg": null,
    "icao_code": null,
    "iata_code": null,
    "gps_code": null,
    "local_code": null,
    "has_scheduled_service": "0",
    "score": "0",
    "home_link": null,
    "wikipedia_link": null,
    "pilot_link": null,
    "keywords": null,
    "zoom": "14",
    "changeMemberRef": "334409",
    "changeDate": "2021-01-21 17:14:08",
    "changeType": "create",
    "changeComment": null,
    "airportRef": "339987",
    "visitor_count": "0",
    "comment_count": "0",
    "home_count": "0",
    "region_code": "BD-2",
    "region_name": "Chittagong Division",
    "region_local_code": "2",
    "region_keywords": "Chittagong bibhag",
    "countryRef": "302622",
    "country_code": "BD",
    "country_name": "Bangladesh",
    "country_keywords": "Bangladeshi airports",
    "continent_code": "AS",
    "continent_name": "Asia",
    "continent_keywords": "Asian airports",
    "has_metar": null,
    "has_taf": null,
    "world_rank": null,
    "continent_rank": null,
    "country_rank": null,
    "region_rank": null
  },
  {
    "contentType": "airport",
    "datatype": "airport",
    "id": "339988",
    "ident": "BD-0007",
    "type": "heliport",
    "name": "Bandarban Heliport",
    "regionRef": "306744",
    "continentRef": "302551",
    "municipality": "Bandarban",
    "latitude_deg": "22.20272",
    "longitude_deg": "92.21449",
    "elevation_ft": null,
    "magnetic_variation_deg": null,
    "icao_code": null,
    "iata_code": null,
    "gps_code": null,
    "local_code": null,
    "has_scheduled_service": "0",
    "score": "0",
    "home_link": null,
    "wikipedia_link": null,
    "pilot_link": null,
    "keywords": null,
    "zoom": "14",
    "changeMemberRef": "334409",
    "changeDate": "2021-01-21 17:14:38",
    "changeType": "create",
    "changeComment": null,
    "airportRef": "339988",
    "visitor_count": "0",
    "comment_count": "0",
    "home_count": "0",
    "region_code": "BD-2",
    "region_name": "Chittagong Division",
    "region_local_code": "2",
    "region_keywords": "Chittagong bibhag",
    "countryRef": "302622",
    "country_code": "BD",
    "country_name": "Bangladesh",
    "country_keywords": "Bangladeshi airports",
    "continent_code": "AS",
    "continent_name": "Asia",
    "continent_keywords": "Asian airports",
    "has_metar": null,
    "has_taf": null,
    "world_rank": null,
    "continent_rank": null,
    "country_rank": null,
    "region_rank": null
  },
  {
    "contentType": "airport",
    "datatype": "airport",
    "id": "339989",
    "ident": "BD-0008",
    "type": "heliport",
    "name": "NVK Helipad",
    "regionRef": "306744",
    "continentRef": "302551",
    "municipality": "Dangar Char",
    "latitude_deg": "22.28432",
    "longitude_deg": "91.80263",
    "elevation_ft": null,
    "magnetic_variation_deg": null,
    "icao_code": null,
    "iata_code": null,
    "gps_code": null,
    "local_code": null,
    "has_scheduled_service": "0",
    "score": "0",
    "home_link": null,
    "wikipedia_link": null,
    "pilot_link": null,
    "keywords": null,
    "zoom": "14",
    "changeMemberRef": "334409",
    "changeDate": "2021-01-21 17:15:30",
    "changeType": "create",
    "changeComment": null,
    "airportRef": "339989",
    "visitor_count": "0",
    "comment_count": "0",
    "home_count": "0",
    "region_code": "BD-2",
    "region_name": "Chittagong Division",
    "region_local_code": "2",
    "region_keywords": "Chittagong bibhag",
    "countryRef": "302622",
    "country_code": "BD",
    "country_name": "Bangladesh",
    "country_keywords": "Bangladeshi airports",
    "continent_code": "AS",
    "continent_name": "Asia",
    "continent_keywords": "Asian airports",
    "has_metar": null,
    "has_taf": null,
    "world_rank": null,
    "continent_rank": null,
    "country_rank": null,
    "region_rank": null
  },
  {
    "contentType": "airport",
    "datatype": "airport",
    "id": "339990",
    "ident": "BD-0009",
    "type": "heliport",
    "name": "BNS Issa Khan Heliport",
    "regionRef": "306744",
    "continentRef": "302551",
    "municipality": "Chattogram (Chittagong)",
    "latitude_deg": "22.28124",
    "longitude_deg": "91.7925",
    "elevation_ft": null,
    "magnetic_variation_deg": null,
    "icao_code": null,
    "iata_code": null,
    "gps_code": null,
    "local_code": null,
    "has_scheduled_service": "0",
    "score": "0",
    "home_link": null,
    "wikipedia_link": null,
    "pilot_link": null,
    "keywords": null,
    "zoom": "14",
    "changeMemberRef": "334409",
    "changeDate": "2021-01-21 17:16:06",
    "changeType": "create",
    "changeComment": null,
    "airportRef": "339990",
    "visitor_count": "0",
    "comment_count": "0",
    "home_count": "0",
    "region_code": "BD-2",
    "region_name": "Chittagong Division",
    "region_local_code": "2",
    "region_keywords": "Chittagong bibhag",
    "countryRef": "302622",
    "country_code": "BD",
    "country_name": "Bangladesh",
    "country_keywords": "Bangladeshi airports",
    "continent_code": "AS",
    "continent_name": "Asia",
    "continent_keywords": "Asian airports",
    "has_metar": null,
    "has_taf": null,
    "world_rank": null,
    "continent_rank": null,
    "country_rank": null,
    "region_rank": null
  },
  {
    "contentType": "airport",
    "datatype": "airport",
    "id": "339991",
    "ident": "BD-0010",
    "type": "heliport",
    "name": "GEC Convention Centre Helipad",
    "regionRef": "306744",
    "continentRef": "302551",
    "municipality": "Chattogram (Chittagong)",
    "latitude_deg": "22.35886",
    "longitude_deg": "91.82005",
    "elevation_ft": null,
    "magnetic_variation_deg": null,
    "icao_code": null,
    "iata_code": null,
    "gps_code": null,
    "local_code": null,
    "has_scheduled_service": "0",
    "score": "0",
    "home_link": null,
    "wikipedia_link": null,
    "pilot_link": null,
    "keywords": null,
    "zoom": "14",
    "changeMemberRef": "334409",
    "changeDate": "2021-01-21 17:17:21",
    "changeType": "create",
    "changeComment": null,
    "airportRef": "339991",
    "visitor_count": "0",
    "comment_count": "0",
    "home_count": "0",
    "region_code": "BD-2",
    "region_name": "Chittagong Division",
    "region_local_code": "2",
    "region_keywords": "Chittagong bibhag",
    "countryRef": "302622",
    "country_code": "BD",
    "country_name": "Bangladesh",
    "country_keywords": "Bangladeshi airports",
    "continent_code": "AS",
    "continent_name": "Asia",
    "continent_keywords": "Asian airports",
    "has_metar": null,
    "has_taf": null,
    "world_rank": null,
    "continent_rank": null,
    "country_rank": null,
    "region_rank": null
  },
  {
    "contentType": "airport",
    "datatype": "airport",
    "id": "339992",
    "ident": "BD-0011",
    "type": "heliport",
    "name": "Bhasan Char Nayamasti Heliport 1",
    "regionRef": "306744",
    "continentRef": "302551",
    "municipality": "Hatiya",
    "latitude_deg": "22.3589",
    "longitude_deg": "91.36826",
    "elevation_ft": null,
    "magnetic_variation_deg": null,
    "icao_code": null,
    "iata_code": null,
    "gps_code": null,
    "local_code": null,
    "has_scheduled_service": "0",
    "score": "0",
    "home_link": null,
    "wikipedia_link": null,
    "pilot_link": null,
    "keywords": null,
    "zoom": "14",
    "changeMemberRef": "334409",
    "changeDate": "2021-01-21 17:20:20",
    "changeType": "update",
    "changeComment": null,
    "airportRef": "339992",
    "visitor_count": "0",
    "comment_count": "0",
    "home_count": "0",
    "region_code": "BD-2",
    "region_name": "Chittagong Division",
    "region_local_code": "2",
    "region_keywords": "Chittagong bibhag",
    "countryRef": "302622",
    "country_code": "BD",
    "country_name": "Bangladesh",
    "country_keywords": "Bangladeshi airports",
    "continent_code": "AS",
    "continent_name": "Asia",
    "continent_keywords": "Asian airports",
    "has_metar": null,
    "has_taf": null,
    "world_rank": null,
    "continent_rank": null,
    "country_rank": null,
    "region_rank": null
  },
  {
    "contentType": "airport",
    "datatype": "airport",
    "id": "349323",
    "ident": "BD-0029",
    "type": "heliport",
    "name": "Tindu Heliport",
    "regionRef": "306744",
    "continentRef": "302551",
    "municipality": "Tindu",
    "latitude_deg": "21.72334",
    "longitude_deg": "92.45736",
    "elevation_ft": "354",
    "magnetic_variation_deg": null,
    "icao_code": null,
    "iata_code": null,
    "gps_code": null,
    "local_code": null,
    "has_scheduled_service": "0",
    "score": "0",
    "home_link": null,
    "wikipedia_link": null,
    "pilot_link": null,
    "keywords": null,
    "zoom": "17",
    "changeMemberRef": "334409",
    "changeDate": "2021-10-29 15:45:48",
    "changeType": "create",
    "changeComment": null,
    "airportRef": "349323",
    "visitor_count": "0",
    "comment_count": "0",
    "home_count": "0",
    "region_code": "BD-2",
    "region_name": "Chittagong Division",
    "region_local_code": "2",
    "region_keywords": "Chittagong bibhag",
    "countryRef": "302622",
    "country_code": "BD",
    "country_name": "Bangladesh",
    "country_keywords": "Bangladeshi airports",
    "continent_code": "AS",
    "continent_name": "Asia",
    "continent_keywords": "Asian airports",
    "has_metar": null,
    "has_taf": null,
    "world_rank": null,
    "continent_rank": null,
    "country_rank": null,
    "region_rank": null
  },
  {
    "contentType": "airport",
    "datatype": "airport",
    "id": "339994",
    "ident": "BD-0013",
    "type": "heliport",
    "name": "Swarna Dweep West Helipad",
    "regionRef": "306744",
    "continentRef": "302551",
    "municipality": "Noakhali",
    "latitude_deg": "22.55542",
    "longitude_deg": "91.29466",
    "elevation_ft": null,
    "magnetic_variation_deg": null,
    "icao_code": null,
    "iata_code": null,
    "gps_code": null,
    "local_code": null,
    "has_scheduled_service": "0",
    "score": "0",
    "home_link": null,
    "wikipedia_link": null,
    "pilot_link": null,
    "keywords": null,
    "zoom": "14",
    "changeMemberRef": "334409",
    "changeDate": "2021-01-21 17:22:04",
    "changeType": "create",
    "changeComment": null,
    "airportRef": "339994",
    "visitor_count": "0",
    "comment_count": "0",
    "home_count": "0",
    "region_code": "BD-2",
    "region_name": "Chittagong Division",
    "region_local_code": "2",
    "region_keywords": "Chittagong bibhag",
    "countryRef": "302622",
    "country_code": "BD",
    "country_name": "Bangladesh",
    "country_keywords": "Bangladeshi airports",
    "continent_code": "AS",
    "continent_name": "Asia",
    "continent_keywords": "Asian airports",
    "has_metar": null,
    "has_taf": null,
    "world_rank": null,
    "continent_rank": null,
    "country_rank": null,
    "region_rank": null
  },
  {
    "contentType": "airport",
    "datatype": "airport",
    "id": "339995",
    "ident": "BD-0014",
    "type": "heliport",
    "name": "Swarna Dweep Water Plant Helipad",
    "regionRef": "306744",
    "continentRef": "302551",
    "municipality": "Noakhali",
    "latitude_deg": "22.54405",
    "longitude_deg": "91.32899",
    "elevation_ft": null,
    "magnetic_variation_deg": null,
    "icao_code": null,
    "iata_code": null,
    "gps_code": null,
    "local_code": null,
    "has_scheduled_service": "0",
    "score": "0",
    "home_link": null,
    "wikipedia_link": null,
    "pilot_link": null,
    "keywords": null,
    "zoom": "14",
    "changeMemberRef": "334409",
    "changeDate": "2021-01-21 17:22:34",
    "changeType": "create",
    "changeComment": null,
    "airportRef": "339995",
    "visitor_count": "0",
    "comment_count": "0",
    "home_count": "0",
    "region_code": "BD-2",
    "region_name": "Chittagong Division",
    "region_local_code": "2",
    "region_keywords": "Chittagong bibhag",
    "countryRef": "302622",
    "country_code": "BD",
    "country_name": "Bangladesh",
    "country_keywords": "Bangladeshi airports",
    "continent_code": "AS",
    "continent_name": "Asia",
    "continent_keywords": "Asian airports",
    "has_metar": null,
    "has_taf": null,
    "world_rank": null,
    "continent_rank": null,
    "country_rank": null,
    "region_rank": null
  },
  {
    "contentType": "airport",
    "datatype": "airport",
    "id": "339996",
    "ident": "BD-0015",
    "type": "heliport",
    "name": "Swarna Dweep North Helipad",
    "regionRef": "306744",
    "continentRef": "302551",
    "municipality": "Noakhali",
    "latitude_deg": "22.57064",
    "longitude_deg": "91.3128",
    "elevation_ft": null,
    "magnetic_variation_deg": null,
    "icao_code": null,
    "iata_code": null,
    "gps_code": null,
    "local_code": null,
    "has_scheduled_service": "0",
    "score": "0",
    "home_link": null,
    "wikipedia_link": null,
    "pilot_link": null,
    "keywords": null,
    "zoom": "14",
    "changeMemberRef": "334409",
    "changeDate": "2021-01-21 17:24:56",
    "changeType": "create",
    "changeComment": null,
    "airportRef": "339996",
    "visitor_count": "0",
    "comment_count": "0",
    "home_count": "0",
    "region_code": "BD-2",
    "region_name": "Chittagong Division",
    "region_local_code": "2",
    "region_keywords": "Chittagong bibhag",
    "countryRef": "302622",
    "country_code": "BD",
    "country_name": "Bangladesh",
    "country_keywords": "Bangladeshi airports",
    "continent_code": "AS",
    "continent_name": "Asia",
    "continent_keywords": "Asian airports",
    "has_metar": null,
    "has_taf": null,
    "world_rank": null,
    "continent_rank": null,
    "country_rank": null,
    "region_rank": null
  },
  {
    "contentType": "airport",
    "datatype": "airport",
    "id": "339997",
    "ident": "BD-0016",
    "type": "heliport",
    "name": "Swarna Dweep Central Helipad",
    "regionRef": "306744",
    "continentRef": "302551",
    "municipality": "Noakhali",
    "latitude_deg": "22.56377",
    "longitude_deg": "91.30638",
    "elevation_ft": null,
    "magnetic_variation_deg": null,
    "icao_code": null,
    "iata_code": null,
    "gps_code": null,
    "local_code": null,
    "has_scheduled_service": "0",
    "score": "0",
    "home_link": null,
    "wikipedia_link": null,
    "pilot_link": null,
    "keywords": null,
    "zoom": "14",
    "changeMemberRef": "334409",
    "changeDate": "2021-01-21 17:25:29",
    "changeType": "create",
    "changeComment": null,
    "airportRef": "339997",
    "visitor_count": "0",
    "comment_count": "0",
    "home_count": "0",
    "region_code": "BD-2",
    "region_name": "Chittagong Division",
    "region_local_code": "2",
    "region_keywords": "Chittagong bibhag",
    "countryRef": "302622",
    "country_code": "BD",
    "country_name": "Bangladesh",
    "country_keywords": "Bangladeshi airports",
    "continent_code": "AS",
    "continent_name": "Asia",
    "continent_keywords": "Asian airports",
    "has_metar": null,
    "has_taf": null,
    "world_rank": null,
    "continent_rank": null,
    "country_rank": null,
    "region_rank": null
  }
]
