[
  {
    "contentType": "airport",
    "datatype": "airport",
    "id": "2908",
    "ident": "FMMI",
    "type": "large_airport",
    "name": "Ivato Airport",
    "regionRef": "304627",
    "continentRef": "302549",
    "municipality": "Antananarivo",
    "latitude_deg": "-18.7969",
    "longitude_deg": "47.478802",
    "elevation_ft": "4198",
    "magnetic_variation_deg": "-14.572",
    "icao_code": "FMMI",
    "iata_code": "TNR",
    "gps_code": "FMMI",
    "local_code": null,
    "has_scheduled_service": "1",
    "score": "1050",
    "home_link": "https://ravinala-airports.aero/en/",
    "wikipedia_link": "https://en.wikipedia.org/wiki/Ivato_Airport",
    "pilot_link": null,
    "keywords": null,
    "zoom": "13",
    "changeMemberRef": "524349",
    "changeDate": "2024-04-30 10:38:54",
    "changeType": "update",
    "changeComment": null,
    "airportRef": "2908",
    "visitor_count": "21",
    "comment_count": "1",
    "home_count": "1",
    "region_code": "MG-T",
    "region_name": "Antananarivo",
    "region_local_code": "T",
    "region_keywords": "Airports in Antananarivo",
    "countryRef": "302585",
    "country_code": "MG",
    "country_name": "Madagascar",
    "country_keywords": "Airports in Madagascar",
    "continent_code": "AF",
    "continent_name": "Africa",
    "continent_keywords": "African airports",
    "has_metar": "FMMI",
    "has_taf": "FMMI",
    "world_rank": "1033",
    "continent_rank": "31",
    "country_rank": "1",
    "region_rank": "1"
  },
  {
    "contentType": "airport",
    "datatype": "airport",
    "id": "2910",
    "ident": "FMMS",
    "type": "medium_airport",
    "name": "Sainte Marie Airport",
    "regionRef": "304623",
    "continentRef": "302549",
    "municipality": "Vohilava",
    "latitude_deg": "-17.093901",
    "longitude_deg": "49.8158",
    "elevation_ft": "7",
    "magnetic_variation_deg": "-13.408",
    "icao_code": "FMMS",
    "iata_code": "SMS",
    "gps_code": "FMMS",
    "local_code": null,
    "has_scheduled_service": "1",
    "score": "750",
    "home_link": null,
    "wikipedia_link": "https://en.wikipedia.org/wiki/Saints_Marie_Airport",
    "pilot_link": null,
    "keywords": null,
    "zoom": "13",
    "changeMemberRef": "342762",
    "changeDate": "2021-04-09 15:27:09",
    "changeType": "update",
    "changeComment": "Added municipality",
    "airportRef": "2910",
    "visitor_count": "1",
    "comment_count": "0",
    "home_count": "0",
    "region_code": "MG-A",
    "region_name": "Toamasina",
    "region_local_code": "A",
    "region_keywords": "Airports in Toamasina",
    "countryRef": "302585",
    "country_code": "MG",
    "country_name": "Madagascar",
    "country_keywords": "Airports in Madagascar",
    "continent_code": "AF",
    "continent_name": "Africa",
    "continent_keywords": "African airports",
    "has_metar": null,
    "has_taf": null,
    "world_rank": "2075",
    "continent_rank": "120",
    "country_rank": "3",
    "region_rank": "1"
  },
  {
    "contentType": "airport",
    "datatype": "airport",
    "id": "2911",
    "ident": "FMMT",
    "type": "medium_airport",
    "name": "Toamasina Ambalamanasy Airport",
    "regionRef": "304623",
    "continentRef": "302549",
    "municipality": "Toamasina",
    "latitude_deg": "-18.109501",
    "longitude_deg": "49.392502",
    "elevation_ft": "22",
    "magnetic_variation_deg": "-14.434",
    "icao_code": "FMMT",
    "iata_code": "TMM",
    "gps_code": "FMMT",
    "local_code": null,
    "has_scheduled_service": "1",
    "score": "750",
    "home_link": null,
    "wikipedia_link": "https://en.wikipedia.org/wiki/Toamasina_Airport",
    "pilot_link": null,
    "keywords": null,
    "zoom": "13",
    "changeMemberRef": "334409",
    "changeDate": "2021-04-13 16:13:37",
    "changeType": "update",
    "changeComment": null,
    "airportRef": "2911",
    "visitor_count": "2",
    "comment_count": "1",
    "home_count": "0",
    "region_code": "MG-A",
    "region_name": "Toamasina",
    "region_local_code": "A",
    "region_keywords": "Airports in Toamasina",
    "countryRef": "302585",
    "country_code": "MG",
    "country_name": "Madagascar",
    "country_keywords": "Airports in Madagascar",
    "continent_code": "AF",
    "continent_name": "Africa",
    "continent_keywords": "African airports",
    "has_metar": "FMMT",
    "has_taf": "FMMT",
    "world_rank": "1032",
    "continent_rank": "32",
    "country_rank": "2",
    "region_rank": "1"
  },
  {
    "contentType": "airport",
    "datatype": "airport",
    "id": "2913",
    "ident": "FMNA",
    "type": "medium_airport",
    "name": "Arrachart Airport",
    "regionRef": "304624",
    "continentRef": "302549",
    "municipality": "Antisiranana",
    "latitude_deg": "-12.3494",
    "longitude_deg": "49.291698",
    "elevation_ft": "374",
    "magnetic_variation_deg": "-8.533",
    "icao_code": "FMNA",
    "iata_code": "DIE",
    "gps_code": "FMNA",
    "local_code": null,
    "has_scheduled_service": "1",
    "score": "750",
    "home_link": null,
    "wikipedia_link": "https://en.wikipedia.org/wiki/Arrachart_Airport",
    "pilot_link": null,
    "keywords": "Diego-Su\u00e1rez",
    "zoom": "13",
    "changeMemberRef": "334409",
    "changeDate": "2021-04-13 16:12:00",
    "changeType": "update",
    "changeComment": null,
    "airportRef": "2913",
    "visitor_count": "2",
    "comment_count": "0",
    "home_count": "0",
    "region_code": "MG-D",
    "region_name": "Antsiranana",
    "region_local_code": "D",
    "region_keywords": "Airports in Antsiranana",
    "countryRef": "302585",
    "country_code": "MG",
    "country_name": "Madagascar",
    "country_keywords": "Airports in Madagascar",
    "continent_code": "AF",
    "continent_name": "Africa",
    "continent_keywords": "African airports",
    "has_metar": "FMNA",
    "has_taf": null,
    "world_rank": "2074",
    "continent_rank": "121",
    "country_rank": "4",
    "region_rank": "1"
  },
  {
    "contentType": "airport",
    "datatype": "airport",
    "id": "2924",
    "ident": "FMNV",
    "type": "medium_airport",
    "name": "Vohemar Airport",
    "regionRef": "304624",
    "continentRef": "302549",
    "municipality": "Vohemar",
    "latitude_deg": "-13.3758",
    "longitude_deg": "50.0028",
    "elevation_ft": "19",
    "magnetic_variation_deg": "-9.594",
    "icao_code": "FMNV",
    "iata_code": "VOH",
    "gps_code": "FMNV",
    "local_code": null,
    "has_scheduled_service": "0",
    "score": "750",
    "home_link": null,
    "wikipedia_link": "https://en.wikipedia.org/wiki/Vohemar_Airport",
    "pilot_link": null,
    "keywords": null,
    "zoom": "13",
    "changeMemberRef": "522325",
    "changeDate": "2025-02-07 21:57:37",
    "changeType": "update",
    "changeComment": null,
    "airportRef": "2924",
    "visitor_count": "0",
    "comment_count": "0",
    "home_count": "0",
    "region_code": "MG-D",
    "region_name": "Antsiranana",
    "region_local_code": "D",
    "region_keywords": "Airports in Antsiranana",
    "countryRef": "302585",
    "country_code": "MG",
    "country_name": "Madagascar",
    "country_keywords": "Airports in Madagascar",
    "continent_code": "AF",
    "continent_name": "Africa",
    "continent_keywords": "African airports",
    "has_metar": null,
    "has_taf": null,
    "world_rank": "3965",
    "continent_rank": "335",
    "country_rank": "18",
    "region_rank": "1"
  },
  {
    "contentType": "airport",
    "datatype": "airport",
    "id": "2928",
    "ident": "FMSF",
    "type": "medium_airport",
    "name": "Fianarantsoa Airport",
    "regionRef": "304625",
    "continentRef": "302549",
    "municipality": "Fianarantsoa",
    "latitude_deg": "-21.441601",
    "longitude_deg": "47.111698",
    "elevation_ft": "3658",
    "magnetic_variation_deg": "-18.15",
    "icao_code": "FMSF",
    "iata_code": "WFI",
    "gps_code": "FMSF",
    "local_code": null,
    "has_scheduled_service": "0",
    "score": "750",
    "home_link": null,
    "wikipedia_link": "https://en.wikipedia.org/wiki/Fianarantsoa_Airport",
    "pilot_link": null,
    "keywords": null,
    "zoom": "13",
    "changeMemberRef": "522325",
    "changeDate": "2025-02-05 19:15:31",
    "changeType": "update",
    "changeComment": null,
    "airportRef": "2928",
    "visitor_count": "1",
    "comment_count": "0",
    "home_count": "0",
    "region_code": "MG-F",
    "region_name": "Fianarantsoa",
    "region_local_code": "F",
    "region_keywords": "Airports in Fianarantsoa",
    "countryRef": "302585",
    "country_code": "MG",
    "country_name": "Madagascar",
    "country_keywords": "Airports in Madagascar",
    "continent_code": "AF",
    "continent_name": "Africa",
    "continent_keywords": "African airports",
    "has_metar": null,
    "has_taf": null,
    "world_rank": "3963",
    "continent_rank": "337",
    "country_rank": "20",
    "region_rank": "1"
  },
  {
    "contentType": "airport",
    "datatype": "airport",
    "id": "2918",
    "ident": "FMNL",
    "type": "medium_airport",
    "name": "Analalava Airport",
    "regionRef": "304626",
    "continentRef": "302549",
    "municipality": "Analalava",
    "latitude_deg": "-14.629514",
    "longitude_deg": "47.763555",
    "elevation_ft": "345",
    "magnetic_variation_deg": "-10.286",
    "icao_code": "FMNL",
    "iata_code": "HVA",
    "gps_code": "FMNL",
    "local_code": null,
    "has_scheduled_service": "0",
    "score": "750",
    "home_link": null,
    "wikipedia_link": "https://en.wikipedia.org/wiki/Analalava_Airport",
    "pilot_link": null,
    "keywords": null,
    "zoom": "16",
    "changeMemberRef": "522325",
    "changeDate": "2025-02-07 21:56:34",
    "changeType": "update",
    "changeComment": null,
    "airportRef": "2918",
    "visitor_count": "0",
    "comment_count": "0",
    "home_count": "0",
    "region_code": "MG-M",
    "region_name": "Mahajanga",
    "region_local_code": "M",
    "region_keywords": "Airports in Mahajanga",
    "countryRef": "302585",
    "country_code": "MG",
    "country_name": "Madagascar",
    "country_keywords": "Airports in Madagascar",
    "continent_code": "AF",
    "continent_name": "Africa",
    "continent_keywords": "African airports",
    "has_metar": null,
    "has_taf": null,
    "world_rank": "3969",
    "continent_rank": "331",
    "country_rank": "14",
    "region_rank": "1"
  },
  {
    "contentType": "airport",
    "datatype": "airport",
    "id": "2919",
    "ident": "FMNM",
    "type": "medium_airport",
    "name": "Amborovy Airport",
    "regionRef": "304626",
    "continentRef": "302549",
    "municipality": "Mahajanga",
    "latitude_deg": "-15.666842",
    "longitude_deg": "46.351233",
    "elevation_ft": "87",
    "magnetic_variation_deg": "-11.028",
    "icao_code": "FMNM",
    "iata_code": "MJN",
    "gps_code": "FMNM",
    "local_code": null,
    "has_scheduled_service": "1",
    "score": "750",
    "home_link": null,
    "wikipedia_link": "https://en.wikipedia.org/wiki/Amborovy_Airport",
    "pilot_link": null,
    "keywords": "Philibert Tsiranana Airport, Mahajanga",
    "zoom": "14",
    "changeMemberRef": "334409",
    "changeDate": "2022-08-10 11:51:45",
    "changeType": "update",
    "changeComment": null,
    "airportRef": "2919",
    "visitor_count": "1",
    "comment_count": "0",
    "home_count": "0",
    "region_code": "MG-M",
    "region_name": "Mahajanga",
    "region_local_code": "M",
    "region_keywords": "Airports in Mahajanga",
    "countryRef": "302585",
    "country_code": "MG",
    "country_name": "Madagascar",
    "country_keywords": "Airports in Madagascar",
    "continent_code": "AF",
    "continent_name": "Africa",
    "continent_keywords": "African airports",
    "has_metar": "FMNM",
    "has_taf": "FMNM",
    "world_rank": "2073",
    "continent_rank": "122",
    "country_rank": "5",
    "region_rank": "1"
  },
  {
    "contentType": "airport",
    "datatype": "airport",
    "id": "2912",
    "ident": "FMMV",
    "type": "medium_airport",
    "name": "Morondava Airport",
    "regionRef": "304628",
    "continentRef": "302549",
    "municipality": "Morondava",
    "latitude_deg": "-20.2847",
    "longitude_deg": "44.3176",
    "elevation_ft": "30",
    "magnetic_variation_deg": "-15.445",
    "icao_code": "FMMV",
    "iata_code": "MOQ",
    "gps_code": "FMMV",
    "local_code": null,
    "has_scheduled_service": "1",
    "score": "750",
    "home_link": null,
    "wikipedia_link": "https://en.wikipedia.org/wiki/Morondava_Airport",
    "pilot_link": null,
    "keywords": null,
    "zoom": "13",
    "changeMemberRef": "334409",
    "changeDate": "2021-02-23 20:25:16",
    "changeType": "update",
    "changeComment": null,
    "airportRef": "2912",
    "visitor_count": "2",
    "comment_count": "0",
    "home_count": "0",
    "region_code": "MG-U",
    "region_name": "Toliara",
    "region_local_code": "U",
    "region_keywords": "Airports in Toliara",
    "countryRef": "302585",
    "country_code": "MG",
    "country_name": "Madagascar",
    "country_keywords": "Airports in Madagascar",
    "continent_code": "AF",
    "continent_name": "Africa",
    "continent_keywords": "African airports",
    "has_metar": null,
    "has_taf": null,
    "world_rank": "2271",
    "continent_rank": "166",
    "country_rank": "7",
    "region_rank": "1"
  },
  {
    "contentType": "airport",
    "datatype": "airport",
    "id": "2914",
    "ident": "FMNC",
    "type": "medium_airport",
    "name": "Mananara Nord Airport",
    "regionRef": "304623",
    "continentRef": "302549",
    "municipality": "Mananara Nord",
    "latitude_deg": "-16.1639",
    "longitude_deg": "49.7738",
    "elevation_ft": "9",
    "magnetic_variation_deg": "-12.393",
    "icao_code": "FMNC",
    "iata_code": "WMR",
    "gps_code": "FMNC",
    "local_code": null,
    "has_scheduled_service": "0",
    "score": "750",
    "home_link": null,
    "wikipedia_link": "https://en.wikipedia.org/wiki/Mananara_Nord_Airport",
    "pilot_link": null,
    "keywords": "Avaratra Airport",
    "zoom": "13",
    "changeMemberRef": "522325",
    "changeDate": "2025-03-18 23:04:38",
    "changeType": "update",
    "changeComment": null,
    "airportRef": "2914",
    "visitor_count": "0",
    "comment_count": "0",
    "home_count": "0",
    "region_code": "MG-A",
    "region_name": "Toamasina",
    "region_local_code": "A",
    "region_keywords": "Airports in Toamasina",
    "countryRef": "302585",
    "country_code": "MG",
    "country_name": "Madagascar",
    "country_keywords": "Airports in Madagascar",
    "continent_code": "AF",
    "continent_name": "Africa",
    "continent_keywords": "African airports",
    "has_metar": null,
    "has_taf": null,
    "world_rank": "3972",
    "continent_rank": "328",
    "country_rank": "11",
    "region_rank": "2"
  },
  {
    "contentType": "airport",
    "datatype": "airport",
    "id": "2922",
    "ident": "FMNR",
    "type": "medium_airport",
    "name": "Maroantsetra Airport",
    "regionRef": "304623",
    "continentRef": "302549",
    "municipality": "Maroantsetra",
    "latitude_deg": "-15.437742",
    "longitude_deg": "49.689081",
    "elevation_ft": "9",
    "magnetic_variation_deg": "-11.524",
    "icao_code": "FMNR",
    "iata_code": "WMN",
    "gps_code": "FMNR",
    "local_code": null,
    "has_scheduled_service": "1",
    "score": "750",
    "home_link": null,
    "wikipedia_link": "https://en.wikipedia.org/wiki/Maroantsetra_Airport",
    "pilot_link": null,
    "keywords": null,
    "zoom": "13",
    "changeMemberRef": "334409",
    "changeDate": "2021-04-13 16:09:25",
    "changeType": "update",
    "changeComment": null,
    "airportRef": "2922",
    "visitor_count": "0",
    "comment_count": "0",
    "home_count": "0",
    "region_code": "MG-A",
    "region_name": "Toamasina",
    "region_local_code": "A",
    "region_keywords": "Airports in Toamasina",
    "countryRef": "302585",
    "country_code": "MG",
    "country_name": "Madagascar",
    "country_keywords": "Airports in Madagascar",
    "continent_code": "AF",
    "continent_name": "Africa",
    "continent_keywords": "African airports",
    "has_metar": null,
    "has_taf": null,
    "world_rank": "3967",
    "continent_rank": "333",
    "country_rank": "16",
    "region_rank": "3"
  },
  {
    "contentType": "airport",
    "datatype": "airport",
    "id": "2917",
    "ident": "FMNH",
    "type": "medium_airport",
    "name": "Antsirabe Airport",
    "regionRef": "304624",
    "continentRef": "302549",
    "municipality": "Antsirabe",
    "latitude_deg": "-14.9994",
    "longitude_deg": "50.320202",
    "elevation_ft": "20",
    "magnetic_variation_deg": "-11.369",
    "icao_code": "FMNH",
    "iata_code": "ANM",
    "gps_code": "FMNH",
    "local_code": null,
    "has_scheduled_service": "0",
    "score": "750",
    "home_link": null,
    "wikipedia_link": "https://en.wikipedia.org/wiki/Antsirabato_Airport",
    "pilot_link": null,
    "keywords": null,
    "zoom": "13",
    "changeMemberRef": "522325",
    "changeDate": "2025-02-07 21:58:10",
    "changeType": "update",
    "changeComment": null,
    "airportRef": "2917",
    "visitor_count": "0",
    "comment_count": "0",
    "home_count": "0",
    "region_code": "MG-D",
    "region_name": "Antsiranana",
    "region_local_code": "D",
    "region_keywords": "Airports in Antsiranana",
    "countryRef": "302585",
    "country_code": "MG",
    "country_name": "Madagascar",
    "country_keywords": "Airports in Madagascar",
    "continent_code": "AF",
    "continent_name": "Africa",
    "continent_keywords": "African airports",
    "has_metar": null,
    "has_taf": null,
    "world_rank": "3970",
    "continent_rank": "330",
    "country_rank": "13",
    "region_rank": "4"
  },
  {
    "contentType": "airport",
    "datatype": "airport",
    "id": "2920",
    "ident": "FMNN",
    "type": "medium_airport",
    "name": "Fascene Airport",
    "regionRef": "304624",
    "continentRef": "302549",
    "municipality": "Nosy Be",
    "latitude_deg": "-13.3121",
    "longitude_deg": "48.3148",
    "elevation_ft": "36",
    "magnetic_variation_deg": "-9.254",
    "icao_code": "FMNN",
    "iata_code": "NOS",
    "gps_code": "FMNN",
    "local_code": null,
    "has_scheduled_service": "1",
    "score": "750",
    "home_link": null,
    "wikipedia_link": "https://en.wikipedia.org/wiki/Fascene_Airport",
    "pilot_link": null,
    "keywords": null,
    "zoom": "14",
    "changeMemberRef": "334409",
    "changeDate": "2022-08-10 11:17:55",
    "changeType": "update",
    "changeComment": null,
    "airportRef": "2920",
    "visitor_count": "6",
    "comment_count": "1",
    "home_count": "0",
    "region_code": "MG-D",
    "region_name": "Antsiranana",
    "region_local_code": "D",
    "region_keywords": "Airports in Antsiranana",
    "countryRef": "302585",
    "country_code": "MG",
    "country_name": "Madagascar",
    "country_keywords": "Airports in Madagascar",
    "continent_code": "AF",
    "continent_name": "Africa",
    "continent_keywords": "African airports",
    "has_metar": "FMNN",
    "has_taf": null,
    "world_rank": "2072",
    "continent_rank": "123",
    "country_rank": "6",
    "region_rank": "2"
  },
  {
    "contentType": "airport",
    "datatype": "airport",
    "id": "2923",
    "ident": "FMNS",
    "type": "medium_airport",
    "name": "Sambava Airport",
    "regionRef": "304624",
    "continentRef": "302549",
    "municipality": "Sambava",
    "latitude_deg": "-14.2786",
    "longitude_deg": "50.174702",
    "elevation_ft": "20",
    "magnetic_variation_deg": "-10.524",
    "icao_code": "FMNS",
    "iata_code": "SVB",
    "gps_code": "FMNS",
    "local_code": null,
    "has_scheduled_service": "1",
    "score": "750",
    "home_link": null,
    "wikipedia_link": "https://en.wikipedia.org/wiki/Sambava_Airport",
    "pilot_link": null,
    "keywords": null,
    "zoom": "13",
    "changeMemberRef": "342762",
    "changeDate": "2021-04-09 16:52:33",
    "changeType": "update",
    "changeComment": "Added municipality",
    "airportRef": "2923",
    "visitor_count": "1",
    "comment_count": "0",
    "home_count": "0",
    "region_code": "MG-D",
    "region_name": "Antsiranana",
    "region_local_code": "D",
    "region_keywords": "Airports in Antsiranana",
    "countryRef": "302585",
    "country_code": "MG",
    "country_name": "Madagascar",
    "country_keywords": "Airports in Madagascar",
    "continent_code": "AF",
    "continent_name": "Africa",
    "continent_keywords": "African airports",
    "has_metar": null,
    "has_taf": null,
    "world_rank": "3966",
    "continent_rank": "334",
    "country_rank": "17",
    "region_rank": "5"
  },
  {
    "contentType": "airport",
    "datatype": "airport",
    "id": "2930",
    "ident": "FMSK",
    "type": "medium_airport",
    "name": "Manakara Airport",
    "regionRef": "304625",
    "continentRef": "302549",
    "municipality": "Manakara",
    "latitude_deg": "-22.119699",
    "longitude_deg": "48.021702",
    "elevation_ft": "33",
    "magnetic_variation_deg": "-19.279",
    "icao_code": "FMSK",
    "iata_code": "WVK",
    "gps_code": "FMSK",
    "local_code": null,
    "has_scheduled_service": "0",
    "score": "750",
    "home_link": null,
    "wikipedia_link": "https://en.wikipedia.org/wiki/Manakara_Airport",
    "pilot_link": null,
    "keywords": null,
    "zoom": "13",
    "changeMemberRef": "522325",
    "changeDate": "2025-02-05 14:47:32",
    "changeType": "update",
    "changeComment": null,
    "airportRef": "2930",
    "visitor_count": "0",
    "comment_count": "0",
    "home_count": "0",
    "region_code": "MG-F",
    "region_name": "Fianarantsoa",
    "region_local_code": "F",
    "region_keywords": "Airports in Fianarantsoa",
    "countryRef": "302585",
    "country_code": "MG",
    "country_name": "Madagascar",
    "country_keywords": "Airports in Madagascar",
    "continent_code": "AF",
    "continent_name": "Africa",
    "continent_keywords": "African airports",
    "has_metar": null,
    "has_taf": null,
    "world_rank": "3962",
    "continent_rank": "338",
    "country_rank": "21",
    "region_rank": "2"
  },
  {
    "contentType": "airport",
    "datatype": "airport",
    "id": "2931",
    "ident": "FMSM",
    "type": "medium_airport",
    "name": "Mananjary Airport",
    "regionRef": "304625",
    "continentRef": "302549",
    "municipality": "Mananjary",
    "latitude_deg": "-21.201799",
    "longitude_deg": "48.358299",
    "elevation_ft": "20",
    "magnetic_variation_deg": "-18.19",
    "icao_code": "FMSM",
    "iata_code": "MNJ",
    "gps_code": "FMSM",
    "local_code": null,
    "has_scheduled_service": "1",
    "score": "750",
    "home_link": null,
    "wikipedia_link": "https://en.wikipedia.org/wiki/Mananjary_Airport",
    "pilot_link": null,
    "keywords": null,
    "zoom": "13",
    "changeMemberRef": "334409",
    "changeDate": "2021-02-23 20:22:59",
    "changeType": "update",
    "changeComment": null,
    "airportRef": "2931",
    "visitor_count": "0",
    "comment_count": "0",
    "home_count": "0",
    "region_code": "MG-F",
    "region_name": "Fianarantsoa",
    "region_local_code": "F",
    "region_keywords": "Airports in Fianarantsoa",
    "countryRef": "302585",
    "country_code": "MG",
    "country_name": "Madagascar",
    "country_keywords": "Airports in Madagascar",
    "continent_code": "AF",
    "continent_name": "Africa",
    "continent_keywords": "African airports",
    "has_metar": null,
    "has_taf": null,
    "world_rank": "3961",
    "continent_rank": "339",
    "country_rank": "22",
    "region_rank": "3"
  },
  {
    "contentType": "airport",
    "datatype": "airport",
    "id": "2921",
    "ident": "FMNQ",
    "type": "medium_airport",
    "name": "Besalampy Airport",
    "regionRef": "304626",
    "continentRef": "302549",
    "municipality": "Besalampy",
    "latitude_deg": "-16.74453",
    "longitude_deg": "44.482484",
    "elevation_ft": "125",
    "magnetic_variation_deg": "-11.321",
    "icao_code": "FMNQ",
    "iata_code": "BPY",
    "gps_code": "FMNQ",
    "local_code": null,
    "has_scheduled_service": "1",
    "score": "750",
    "home_link": null,
    "wikipedia_link": "https://en.wikipedia.org/wiki/Besalampy_Airport",
    "pilot_link": null,
    "keywords": null,
    "zoom": "13",
    "changeMemberRef": "342762",
    "changeDate": "2021-04-09 16:49:52",
    "changeType": "update",
    "changeComment": "Added municipality",
    "airportRef": "2921",
    "visitor_count": "0",
    "comment_count": "0",
    "home_count": "0",
    "region_code": "MG-M",
    "region_name": "Mahajanga",
    "region_local_code": "M",
    "region_keywords": "Airports in Mahajanga",
    "countryRef": "302585",
    "country_code": "MG",
    "country_name": "Madagascar",
    "country_keywords": "Airports in Madagascar",
    "continent_code": "AF",
    "continent_name": "Africa",
    "continent_keywords": "African airports",
    "has_metar": null,
    "has_taf": null,
    "world_rank": "3968",
    "continent_rank": "332",
    "country_rank": "15",
    "region_rank": "2"
  },
  {
    "contentType": "airport",
    "datatype": "airport",
    "id": "2925",
    "ident": "FMNW",
    "type": "medium_airport",
    "name": "Ambalabe Airport",
    "regionRef": "304626",
    "continentRef": "302549",
    "municipality": "Antsohihy",
    "latitude_deg": "-14.8988",
    "longitude_deg": "47.9939",
    "elevation_ft": "92",
    "magnetic_variation_deg": "-10.488",
    "icao_code": "FMNW",
    "iata_code": "WAI",
    "gps_code": "FMNW",
    "local_code": null,
    "has_scheduled_service": "0",
    "score": "750",
    "home_link": null,
    "wikipedia_link": "https://en.wikipedia.org/wiki/Ambalabe_Airport",
    "pilot_link": null,
    "keywords": null,
    "zoom": "13",
    "changeMemberRef": "522325",
    "changeDate": "2025-03-18 23:04:07",
    "changeType": "update",
    "changeComment": null,
    "airportRef": "2925",
    "visitor_count": "0",
    "comment_count": "0",
    "home_count": "0",
    "region_code": "MG-M",
    "region_name": "Mahajanga",
    "region_local_code": "M",
    "region_keywords": "Airports in Mahajanga",
    "countryRef": "302585",
    "country_code": "MG",
    "country_name": "Madagascar",
    "country_keywords": "Airports in Madagascar",
    "continent_code": "AF",
    "continent_name": "Africa",
    "continent_keywords": "African airports",
    "has_metar": null,
    "has_taf": null,
    "world_rank": "3964",
    "continent_rank": "336",
    "country_rank": "19",
    "region_rank": "3"
  },
  {
    "contentType": "airport",
    "datatype": "airport",
    "id": "2909",
    "ident": "FMMN",
    "type": "medium_airport",
    "name": "Miandrivazo Airport",
    "regionRef": "304628",
    "continentRef": "302549",
    "municipality": "Miandrivazo",
    "latitude_deg": "-19.562799",
    "longitude_deg": "45.450802",
    "elevation_ft": "203",
    "magnetic_variation_deg": "-15.133",
    "icao_code": "FMMN",
    "iata_code": "ZVA",
    "gps_code": "FMMN",
    "local_code": null,
    "has_scheduled_service": "0",
    "score": "750",
    "home_link": null,
    "wikipedia_link": "https://en.wikipedia.org/wiki/Miandrivazo_Airport",
    "pilot_link": null,
    "keywords": null,
    "zoom": "13",
    "changeMemberRef": "522325",
    "changeDate": "2025-03-18 23:01:21",
    "changeType": "update",
    "changeComment": null,
    "airportRef": "2909",
    "visitor_count": "0",
    "comment_count": "0",
    "home_count": "0",
    "region_code": "MG-U",
    "region_name": "Toliara",
    "region_local_code": "U",
    "region_keywords": "Airports in Toliara",
    "countryRef": "302585",
    "country_code": "MG",
    "country_name": "Madagascar",
    "country_keywords": "Airports in Madagascar",
    "continent_code": "AF",
    "continent_name": "Africa",
    "continent_keywords": "African airports",
    "has_metar": null,
    "has_taf": null,
    "world_rank": "3973",
    "continent_rank": "327",
    "country_rank": "10",
    "region_rank": "4"
  },
  {
    "contentType": "airport",
    "datatype": "airport",
    "id": "2927",
    "ident": "FMSD",
    "type": "medium_airport",
    "name": "T\u00f4lanaro Airport",
    "regionRef": "304628",
    "continentRef": "302549",
    "municipality": "T\u00f4lanaro",
    "latitude_deg": "-25.038099",
    "longitude_deg": "46.9561",
    "elevation_ft": "29",
    "magnetic_variation_deg": "-23.187",
    "icao_code": "FMSD",
    "iata_code": "FTU",
    "gps_code": "FMSD",
    "local_code": null,
    "has_scheduled_service": "1",
    "score": "750",
    "home_link": null,
    "wikipedia_link": "https://en.wikipedia.org/wiki/T%C3%B4lanaro_Airport",
    "pilot_link": null,
    "keywords": "Tolagnaro Airport, Marillac Airport, Fort-Dauphin",
    "zoom": "13",
    "changeMemberRef": "334409",
    "changeDate": "2021-04-13 16:14:43",
    "changeType": "update",
    "changeComment": null,
    "airportRef": "2927",
    "visitor_count": "2",
    "comment_count": "0",
    "home_count": "0",
    "region_code": "MG-U",
    "region_name": "Toliara",
    "region_local_code": "U",
    "region_keywords": "Airports in Toliara",
    "countryRef": "302585",
    "country_code": "MG",
    "country_name": "Madagascar",
    "country_keywords": "Airports in Madagascar",
    "continent_code": "AF",
    "continent_name": "Africa",
    "continent_keywords": "African airports",
    "has_metar": "FMSD",
    "has_taf": null,
    "world_rank": "2386",
    "continent_rank": "188",
    "country_rank": "8",
    "region_rank": "2"
  },
  {
    "contentType": "airport",
    "datatype": "airport",
    "id": "2932",
    "ident": "FMSR",
    "type": "medium_airport",
    "name": "Morombe Airport",
    "regionRef": "304628",
    "continentRef": "302549",
    "municipality": "Morombe",
    "latitude_deg": "-21.753837",
    "longitude_deg": "43.374753",
    "elevation_ft": "16",
    "magnetic_variation_deg": "-17.22",
    "icao_code": "FMSR",
    "iata_code": "MXM",
    "gps_code": "FMSR",
    "local_code": null,
    "has_scheduled_service": "0",
    "score": "750",
    "home_link": null,
    "wikipedia_link": "https://en.wikipedia.org/wiki/Morombe_Airport",
    "pilot_link": null,
    "keywords": null,
    "zoom": "13",
    "changeMemberRef": "522325",
    "changeDate": "2025-03-18 23:05:42",
    "changeType": "update",
    "changeComment": null,
    "airportRef": "2932",
    "visitor_count": "1",
    "comment_count": "0",
    "home_count": "0",
    "region_code": "MG-U",
    "region_name": "Toliara",
    "region_local_code": "U",
    "region_keywords": "Airports in Toliara",
    "countryRef": "302585",
    "country_code": "MG",
    "country_name": "Madagascar",
    "country_keywords": "Airports in Madagascar",
    "continent_code": "AF",
    "continent_name": "Africa",
    "continent_keywords": "African airports",
    "has_metar": null,
    "has_taf": null,
    "world_rank": "3960",
    "continent_rank": "340",
    "country_rank": "23",
    "region_rank": "5"
  },
  {
    "contentType": "airport",
    "datatype": "airport",
    "id": "2933",
    "ident": "FMST",
    "type": "medium_airport",
    "name": "Toliara Airport",
    "regionRef": "304628",
    "continentRef": "302549",
    "municipality": "Toliara",
    "latitude_deg": "-23.3834",
    "longitude_deg": "43.7285",
    "elevation_ft": "29",
    "magnetic_variation_deg": "-19.48",
    "icao_code": "FMST",
    "iata_code": "TLE",
    "gps_code": "FMST",
    "local_code": null,
    "has_scheduled_service": "1",
    "score": "750",
    "home_link": null,
    "wikipedia_link": "https://en.wikipedia.org/wiki/Toliara_Airport",
    "pilot_link": null,
    "keywords": null,
    "zoom": "13",
    "changeMemberRef": "334409",
    "changeDate": "2021-02-23 20:26:06",
    "changeType": "update",
    "changeComment": null,
    "airportRef": "2933",
    "visitor_count": "2",
    "comment_count": "0",
    "home_count": "0",
    "region_code": "MG-U",
    "region_name": "Toliara",
    "region_local_code": "U",
    "region_keywords": "Airports in Toliara",
    "countryRef": "302585",
    "country_code": "MG",
    "country_name": "Madagascar",
    "country_keywords": "Airports in Madagascar",
    "continent_code": "AF",
    "continent_name": "Africa",
    "continent_keywords": "African airports",
    "has_metar": null,
    "has_taf": null,
    "world_rank": "2710",
    "continent_rank": "227",
    "country_rank": "9",
    "region_rank": "3"
  },
  {
    "contentType": "airport",
    "datatype": "airport",
    "id": "2915",
    "ident": "FMND",
    "type": "medium_airport",
    "name": "Andapa Airport",
    "regionRef": "304624",
    "continentRef": "302549",
    "municipality": null,
    "latitude_deg": "-14.651700019836426",
    "longitude_deg": "49.620601654052734",
    "elevation_ft": "1552",
    "magnetic_variation_deg": "-11.042",
    "icao_code": "FMND",
    "iata_code": "ZWA",
    "gps_code": "FMND",
    "local_code": null,
    "has_scheduled_service": "0",
    "score": "250",
    "home_link": null,
    "wikipedia_link": null,
    "pilot_link": null,
    "keywords": null,
    "zoom": "13",
    "changeMemberRef": null,
    "changeDate": "2008-06-13 14:30:04",
    "changeType": "create",
    "changeComment": "Initial version",
    "airportRef": "2915",
    "visitor_count": "0",
    "comment_count": "0",
    "home_count": "0",
    "region_code": "MG-D",
    "region_name": "Antsiranana",
    "region_local_code": "D",
    "region_keywords": "Airports in Antsiranana",
    "countryRef": "302585",
    "country_code": "MG",
    "country_name": "Madagascar",
    "country_keywords": "Airports in Madagascar",
    "continent_code": "AF",
    "continent_name": "Africa",
    "continent_keywords": "African airports",
    "has_metar": null,
    "has_taf": null,
    "world_rank": "3971",
    "continent_rank": "329",
    "country_rank": "12",
    "region_rank": "3"
  },
  {
    "contentType": "airport",
    "datatype": "airport",
    "id": "2929",
    "ident": "FMSG",
    "type": "small_airport",
    "name": "Farafangana Airport",
    "regionRef": "304625",
    "continentRef": "302549",
    "municipality": "Farafangana",
    "latitude_deg": "-22.8053",
    "longitude_deg": "47.820599",
    "elevation_ft": "26",
    "magnetic_variation_deg": "-20.216",
    "icao_code": "FMSG",
    "iata_code": "RVA",
    "gps_code": "FMSG",
    "local_code": null,
    "has_scheduled_service": "0",
    "score": "150",
    "home_link": null,
    "wikipedia_link": "https://en.wikipedia.org/wiki/Farafangana_Airport",
    "pilot_link": null,
    "keywords": null,
    "zoom": "14",
    "changeMemberRef": "522325",
    "changeDate": "2025-02-05 14:47:59",
    "changeType": "update",
    "changeComment": null,
    "airportRef": "2929",
    "visitor_count": "0",
    "comment_count": "0",
    "home_count": "0",
    "region_code": "MG-F",
    "region_name": "Fianarantsoa",
    "region_local_code": "F",
    "region_keywords": "Airports in Fianarantsoa",
    "countryRef": "302585",
    "country_code": "MG",
    "country_name": "Madagascar",
    "country_keywords": "Airports in Madagascar",
    "continent_code": "AF",
    "continent_name": "Africa",
    "continent_keywords": "African airports",
    "has_metar": null,
    "has_taf": null,
    "world_rank": "6064",
    "continent_rank": "493",
    "country_rank": "27",
    "region_rank": "4"
  },
  {
    "contentType": "airport",
    "datatype": "airport",
    "id": "2907",
    "ident": "FMMA",
    "type": "small_airport",
    "name": "Antananarivo Arivonimamo Airport",
    "regionRef": "304627",
    "continentRef": "302549",
    "municipality": "Arivonimamo",
    "latitude_deg": "-19.028999",
    "longitude_deg": "47.171799",
    "elevation_ft": "4757",
    "magnetic_variation_deg": "-15.082",
    "icao_code": null,
    "iata_code": null,
    "gps_code": "FMMA",
    "local_code": null,
    "has_scheduled_service": "0",
    "score": "50",
    "home_link": null,
    "wikipedia_link": "https://en.wikipedia.org/wiki/Arivonimamo_Air_Base",
    "pilot_link": null,
    "keywords": null,
    "zoom": "14",
    "changeMemberRef": "524349",
    "changeDate": "2024-05-18 15:31:51",
    "changeType": "update",
    "changeComment": "wikipedia link added",
    "airportRef": "2907",
    "visitor_count": "2",
    "comment_count": "0",
    "home_count": "0",
    "region_code": "MG-T",
    "region_name": "Antananarivo",
    "region_local_code": "T",
    "region_keywords": "Airports in Antananarivo",
    "countryRef": "302585",
    "country_code": "MG",
    "country_name": "Madagascar",
    "country_keywords": "Airports in Madagascar",
    "continent_code": "AF",
    "continent_name": "Africa",
    "continent_keywords": "African airports",
    "has_metar": null,
    "has_taf": null,
    "world_rank": "6067",
    "continent_rank": "490",
    "country_rank": "24",
    "region_rank": "2"
  },
  {
    "contentType": "airport",
    "datatype": "airport",
    "id": "31912",
    "ident": "FMSJ",
    "type": "small_airport",
    "name": "Manja Airport",
    "regionRef": "304628",
    "continentRef": "302549",
    "municipality": "Manja",
    "latitude_deg": "-21.426105",
    "longitude_deg": "44.316509",
    "elevation_ft": "787",
    "magnetic_variation_deg": null,
    "icao_code": "FMSJ",
    "iata_code": "MJA",
    "gps_code": "FMSJ",
    "local_code": null,
    "has_scheduled_service": "0",
    "score": "150",
    "home_link": null,
    "wikipedia_link": "https://en.wikipedia.org/wiki/Manja_Airport",
    "pilot_link": null,
    "keywords": null,
    "zoom": "14",
    "changeMemberRef": "522325",
    "changeDate": "2025-02-07 21:55:20",
    "changeType": "update",
    "changeComment": null,
    "airportRef": "31912",
    "visitor_count": "0",
    "comment_count": "0",
    "home_count": "0",
    "region_code": "MG-U",
    "region_name": "Toliara",
    "region_local_code": "U",
    "region_keywords": "Airports in Toliara",
    "countryRef": "302585",
    "country_code": "MG",
    "country_name": "Madagascar",
    "country_keywords": "Airports in Madagascar",
    "continent_code": "AF",
    "continent_name": "Africa",
    "continent_keywords": "African airports",
    "has_metar": null,
    "has_taf": null,
    "world_rank": null,
    "continent_rank": null,
    "country_rank": null,
    "region_rank": null
  },
  {
    "contentType": "airport",
    "datatype": "airport",
    "id": "31982",
    "ident": "FMMO",
    "type": "small_airport",
    "name": "Maintirano Airport",
    "regionRef": "304626",
    "continentRef": "302549",
    "municipality": "Maintirano",
    "latitude_deg": "-18.049999",
    "longitude_deg": "44.033001",
    "elevation_ft": "95",
    "magnetic_variation_deg": null,
    "icao_code": "FMMO",
    "iata_code": "MXT",
    "gps_code": "FMMO",
    "local_code": null,
    "has_scheduled_service": "0",
    "score": "150",
    "home_link": null,
    "wikipedia_link": "https://en.wikipedia.org/wiki/Maintirano_Airport",
    "pilot_link": null,
    "keywords": null,
    "zoom": "14",
    "changeMemberRef": "522325",
    "changeDate": "2025-03-18 23:06:14",
    "changeType": "update",
    "changeComment": null,
    "airportRef": "31982",
    "visitor_count": "0",
    "comment_count": "0",
    "home_count": "0",
    "region_code": "MG-M",
    "region_name": "Mahajanga",
    "region_local_code": "M",
    "region_keywords": "Airports in Mahajanga",
    "countryRef": "302585",
    "country_code": "MG",
    "country_name": "Madagascar",
    "country_keywords": "Airports in Madagascar",
    "continent_code": "AF",
    "continent_name": "Africa",
    "continent_keywords": "African airports",
    "has_metar": null,
    "has_taf": null,
    "world_rank": null,
    "continent_rank": null,
    "country_rank": null,
    "region_rank": null
  },
  {
    "contentType": "airport",
    "datatype": "airport",
    "id": "32481",
    "ident": "FMNT",
    "type": "small_airport",
    "name": "Tsaratanana Airport",
    "regionRef": "304626",
    "continentRef": "302549",
    "municipality": "Tsaratanana",
    "latitude_deg": "-16.751064",
    "longitude_deg": "47.619016",
    "elevation_ft": "1073",
    "magnetic_variation_deg": null,
    "icao_code": "FMNT",
    "iata_code": "TTS",
    "gps_code": "FMNT",
    "local_code": null,
    "has_scheduled_service": "1",
    "score": "150",
    "home_link": null,
    "wikipedia_link": "https://en.wikipedia.org/wiki/Tsaratanana_Airport",
    "pilot_link": null,
    "keywords": null,
    "zoom": "14",
    "changeMemberRef": "329245",
    "changeDate": "2018-09-16 03:11:48",
    "changeType": "update",
    "changeComment": null,
    "airportRef": "32481",
    "visitor_count": "0",
    "comment_count": "0",
    "home_count": "0",
    "region_code": "MG-M",
    "region_name": "Mahajanga",
    "region_local_code": "M",
    "region_keywords": "Airports in Mahajanga",
    "countryRef": "302585",
    "country_code": "MG",
    "country_name": "Madagascar",
    "country_keywords": "Airports in Madagascar",
    "continent_code": "AF",
    "continent_name": "Africa",
    "continent_keywords": "African airports",
    "has_metar": null,
    "has_taf": null,
    "world_rank": null,
    "continent_rank": null,
    "country_rank": null,
    "region_rank": null
  },
  {
    "contentType": "airport",
    "datatype": "airport",
    "id": "32484",
    "ident": "FMMR",
    "type": "small_airport",
    "name": "Morafenobe Airport",
    "regionRef": "304626",
    "continentRef": "302549",
    "municipality": "Morafenobe",
    "latitude_deg": "-17.850083",
    "longitude_deg": "44.920467",
    "elevation_ft": "748",
    "magnetic_variation_deg": null,
    "icao_code": "FMMR",
    "iata_code": "TVA",
    "gps_code": "FMMR",
    "local_code": null,
    "has_scheduled_service": "0",
    "score": "150",
    "home_link": null,
    "wikipedia_link": "https://en.wikipedia.org/wiki/Morafenobe_Airport",
    "pilot_link": null,
    "keywords": null,
    "zoom": "14",
    "changeMemberRef": "522325",
    "changeDate": "2025-03-18 23:02:32",
    "changeType": "update",
    "changeComment": null,
    "airportRef": "32484",
    "visitor_count": "0",
    "comment_count": "0",
    "home_count": "0",
    "region_code": "MG-M",
    "region_name": "Mahajanga",
    "region_local_code": "M",
    "region_keywords": "Airports in Mahajanga",
    "countryRef": "302585",
    "country_code": "MG",
    "country_name": "Madagascar",
    "country_keywords": "Airports in Madagascar",
    "continent_code": "AF",
    "continent_name": "Africa",
    "continent_keywords": "African airports",
    "has_metar": null,
    "has_taf": null,
    "world_rank": null,
    "continent_rank": null,
    "country_rank": null,
    "region_rank": null
  },
  {
    "contentType": "airport",
    "datatype": "airport",
    "id": "32659",
    "ident": "FMNX",
    "type": "small_airport",
    "name": "Mandritsara Airport",
    "regionRef": "304626",
    "continentRef": "302549",
    "municipality": "Mandritsara",
    "latitude_deg": "-15.845992",
    "longitude_deg": "48.834718",
    "elevation_ft": "1007",
    "magnetic_variation_deg": null,
    "icao_code": "FMNX",
    "iata_code": "WMA",
    "gps_code": "FMNX",
    "local_code": null,
    "has_scheduled_service": "0",
    "score": "150",
    "home_link": null,
    "wikipedia_link": "https://en.wikipedia.org/wiki/Mandritsara_Airport",
    "pilot_link": null,
    "keywords": null,
    "zoom": "14",
    "changeMemberRef": "522325",
    "changeDate": "2025-02-07 21:58:46",
    "changeType": "update",
    "changeComment": null,
    "airportRef": "32659",
    "visitor_count": "0",
    "comment_count": "0",
    "home_count": "0",
    "region_code": "MG-M",
    "region_name": "Mahajanga",
    "region_local_code": "M",
    "region_keywords": "Airports in Mahajanga",
    "countryRef": "302585",
    "country_code": "MG",
    "country_name": "Madagascar",
    "country_keywords": "Airports in Madagascar",
    "continent_code": "AF",
    "continent_name": "Africa",
    "continent_keywords": "African airports",
    "has_metar": null,
    "has_taf": null,
    "world_rank": null,
    "continent_rank": null,
    "country_rank": null,
    "region_rank": null
  },
  {
    "contentType": "airport",
    "datatype": "airport",
    "id": "32673",
    "ident": "FMNG",
    "type": "small_airport",
    "name": "Port Berg\u00e9 Airport",
    "regionRef": "304626",
    "continentRef": "302549",
    "municipality": "Port Berg\u00e9",
    "latitude_deg": "-15.584286",
    "longitude_deg": "47.623587",
    "elevation_ft": "213",
    "magnetic_variation_deg": null,
    "icao_code": "FMNG",
    "iata_code": "WPB",
    "gps_code": "FMNG",
    "local_code": null,
    "has_scheduled_service": "0",
    "score": "150",
    "home_link": null,
    "wikipedia_link": "https://en.wikipedia.org/wiki/Port_Berg\u00e9_Airport",
    "pilot_link": null,
    "keywords": null,
    "zoom": "14",
    "changeMemberRef": "522325",
    "changeDate": "2025-03-18 23:03:41",
    "changeType": "update",
    "changeComment": null,
    "airportRef": "32673",
    "visitor_count": "0",
    "comment_count": "0",
    "home_count": "0",
    "region_code": "MG-M",
    "region_name": "Mahajanga",
    "region_local_code": "M",
    "region_keywords": "Airports in Mahajanga",
    "countryRef": "302585",
    "country_code": "MG",
    "country_name": "Madagascar",
    "country_keywords": "Airports in Madagascar",
    "continent_code": "AF",
    "continent_name": "Africa",
    "continent_keywords": "African airports",
    "has_metar": null,
    "has_taf": null,
    "world_rank": null,
    "continent_rank": null,
    "country_rank": null,
    "region_rank": null
  },
  {
    "contentType": "airport",
    "datatype": "airport",
    "id": "32678",
    "ident": "FMMU",
    "type": "small_airport",
    "name": "Tambohorano Airport",
    "regionRef": "304626",
    "continentRef": "302549",
    "municipality": "Tambohorano",
    "latitude_deg": "-17.476101",
    "longitude_deg": "43.972801",
    "elevation_ft": "23",
    "magnetic_variation_deg": null,
    "icao_code": "FMMU",
    "iata_code": "WTA",
    "gps_code": "FMMU",
    "local_code": null,
    "has_scheduled_service": "1",
    "score": "150",
    "home_link": null,
    "wikipedia_link": "https://en.wikipedia.org/wiki/Tambohorano_Airport",
    "pilot_link": null,
    "keywords": null,
    "zoom": "14",
    "changeMemberRef": "524349",
    "changeDate": "2024-04-07 14:38:42",
    "changeType": "update",
    "changeComment": null,
    "airportRef": "32678",
    "visitor_count": "0",
    "comment_count": "0",
    "home_count": "0",
    "region_code": "MG-M",
    "region_name": "Mahajanga",
    "region_local_code": "M",
    "region_keywords": "Airports in Mahajanga",
    "countryRef": "302585",
    "country_code": "MG",
    "country_name": "Madagascar",
    "country_keywords": "Airports in Madagascar",
    "continent_code": "AF",
    "continent_name": "Africa",
    "continent_keywords": "African airports",
    "has_metar": null,
    "has_taf": null,
    "world_rank": null,
    "continent_rank": null,
    "country_rank": null,
    "region_rank": null
  },
  {
    "contentType": "airport",
    "datatype": "airport",
    "id": "35210",
    "ident": "FMNP",
    "type": "small_airport",
    "name": "Mampikony Airport",
    "regionRef": "304626",
    "continentRef": "302549",
    "municipality": "Mampikony",
    "latitude_deg": "-16.072269",
    "longitude_deg": "47.644165",
    "elevation_ft": null,
    "magnetic_variation_deg": null,
    "icao_code": "FMNP",
    "iata_code": "WMP",
    "gps_code": "FMNP",
    "local_code": null,
    "has_scheduled_service": "0",
    "score": "150",
    "home_link": null,
    "wikipedia_link": "https://en.wikipedia.org/wiki/Mampikony_Airport",
    "pilot_link": null,
    "keywords": null,
    "zoom": "14",
    "changeMemberRef": "522325",
    "changeDate": "2025-02-07 21:55:53",
    "changeType": "update",
    "changeComment": null,
    "airportRef": "35210",
    "visitor_count": "0",
    "comment_count": "0",
    "home_count": "0",
    "region_code": "MG-M",
    "region_name": "Mahajanga",
    "region_local_code": "M",
    "region_keywords": "Airports in Mahajanga",
    "countryRef": "302585",
    "country_code": "MG",
    "country_name": "Madagascar",
    "country_keywords": "Airports in Madagascar",
    "continent_code": "AF",
    "continent_name": "Africa",
    "continent_keywords": "African airports",
    "has_metar": null,
    "has_taf": null,
    "world_rank": null,
    "continent_rank": null,
    "country_rank": null,
    "region_rank": null
  },
  {
    "contentType": "airport",
    "datatype": "airport",
    "id": "32633",
    "ident": "FMMG",
    "type": "small_airport",
    "name": "Antsalova Airport",
    "regionRef": "304626",
    "continentRef": "302549",
    "municipality": "Antsalova",
    "latitude_deg": "-18.701273",
    "longitude_deg": "44.614921",
    "elevation_ft": "551",
    "magnetic_variation_deg": null,
    "icao_code": "FMMG",
    "iata_code": "WAQ",
    "gps_code": "FMMG",
    "local_code": null,
    "has_scheduled_service": "0",
    "score": "150",
    "home_link": null,
    "wikipedia_link": "https://en.wikipedia.org/wiki/Antsalova_Airport",
    "pilot_link": null,
    "keywords": null,
    "zoom": "14",
    "changeMemberRef": "522325",
    "changeDate": "2025-03-18 23:02:03",
    "changeType": "update",
    "changeComment": null,
    "airportRef": "32633",
    "visitor_count": "0",
    "comment_count": "0",
    "home_count": "0",
    "region_code": "MG-M",
    "region_name": "Mahajanga",
    "region_local_code": "M",
    "region_keywords": "Airports in Mahajanga",
    "countryRef": "302585",
    "country_code": "MG",
    "country_name": "Madagascar",
    "country_keywords": "Airports in Madagascar",
    "continent_code": "AF",
    "continent_name": "Africa",
    "continent_keywords": "African airports",
    "has_metar": null,
    "has_taf": null,
    "world_rank": null,
    "continent_rank": null,
    "country_rank": null,
    "region_rank": null
  },
  {
    "contentType": "airport",
    "datatype": "airport",
    "id": "31715",
    "ident": "FMMK",
    "type": "small_airport",
    "name": "Ankavandra Airport",
    "regionRef": "304628",
    "continentRef": "302549",
    "municipality": "Ankavandra",
    "latitude_deg": "-18.80501",
    "longitude_deg": "45.273467",
    "elevation_ft": "427",
    "magnetic_variation_deg": null,
    "icao_code": "FMMK",
    "iata_code": "JVA",
    "gps_code": "FMMK",
    "local_code": null,
    "has_scheduled_service": "0",
    "score": "150",
    "home_link": null,
    "wikipedia_link": "https://en.wikipedia.org/wiki/Ankavandra_Airport",
    "pilot_link": null,
    "keywords": null,
    "zoom": "14",
    "changeMemberRef": "522325",
    "changeDate": "2025-02-07 21:59:52",
    "changeType": "update",
    "changeComment": null,
    "airportRef": "31715",
    "visitor_count": "0",
    "comment_count": "0",
    "home_count": "0",
    "region_code": "MG-U",
    "region_name": "Toliara",
    "region_local_code": "U",
    "region_keywords": "Airports in Toliara",
    "countryRef": "302585",
    "country_code": "MG",
    "country_name": "Madagascar",
    "country_keywords": "Airports in Madagascar",
    "continent_code": "AF",
    "continent_name": "Africa",
    "continent_keywords": "African airports",
    "has_metar": null,
    "has_taf": null,
    "world_rank": null,
    "continent_rank": null,
    "country_rank": null,
    "region_rank": null
  },
  {
    "contentType": "airport",
    "datatype": "airport",
    "id": "30774",
    "ident": "FMML",
    "type": "small_airport",
    "name": "Belo sur Tsiribihina Airport",
    "regionRef": "304628",
    "continentRef": "302549",
    "municipality": "Belo sur Tsiribihina",
    "latitude_deg": "-19.686701",
    "longitude_deg": "44.541901",
    "elevation_ft": "154",
    "magnetic_variation_deg": null,
    "icao_code": "FMML",
    "iata_code": "BMD",
    "gps_code": "FMML",
    "local_code": null,
    "has_scheduled_service": "0",
    "score": "150",
    "home_link": null,
    "wikipedia_link": "https://en.wikipedia.org/wiki/Belo_sur_Tsiribihina_Airport",
    "pilot_link": null,
    "keywords": null,
    "zoom": "14",
    "changeMemberRef": "522325",
    "changeDate": "2025-02-07 21:54:59",
    "changeType": "update",
    "changeComment": null,
    "airportRef": "30774",
    "visitor_count": "0",
    "comment_count": "0",
    "home_count": "0",
    "region_code": "MG-U",
    "region_name": "Toliara",
    "region_local_code": "U",
    "region_keywords": "Airports in Toliara",
    "countryRef": "302585",
    "country_code": "MG",
    "country_name": "Madagascar",
    "country_keywords": "Airports in Madagascar",
    "continent_code": "AF",
    "continent_name": "Africa",
    "continent_keywords": "African airports",
    "has_metar": null,
    "has_taf": null,
    "world_rank": null,
    "continent_rank": null,
    "country_rank": null,
    "region_rank": null
  },
  {
    "contentType": "airport",
    "datatype": "airport",
    "id": "32682",
    "ident": "FMMX",
    "type": "small_airport",
    "name": "Tsiroanomandidy Airport",
    "regionRef": "304627",
    "continentRef": "302549",
    "municipality": "Tsiroanomandidy",
    "latitude_deg": "-18.759677",
    "longitude_deg": "46.054065",
    "elevation_ft": "2776",
    "magnetic_variation_deg": null,
    "icao_code": "FMMX",
    "iata_code": "WTS",
    "gps_code": "FMMX",
    "local_code": null,
    "has_scheduled_service": "0",
    "score": "150",
    "home_link": null,
    "wikipedia_link": "https://en.wikipedia.org/wiki/Tsiroanomandidy_Airport",
    "pilot_link": null,
    "keywords": null,
    "zoom": "14",
    "changeMemberRef": "522325",
    "changeDate": "2025-03-18 22:59:28",
    "changeType": "update",
    "changeComment": null,
    "airportRef": "32682",
    "visitor_count": "1",
    "comment_count": "0",
    "home_count": "0",
    "region_code": "MG-T",
    "region_name": "Antananarivo",
    "region_local_code": "T",
    "region_keywords": "Airports in Antananarivo",
    "countryRef": "302585",
    "country_code": "MG",
    "country_name": "Madagascar",
    "country_keywords": "Airports in Madagascar",
    "continent_code": "AF",
    "continent_name": "Africa",
    "continent_keywords": "African airports",
    "has_metar": null,
    "has_taf": null,
    "world_rank": null,
    "continent_rank": null,
    "country_rank": null,
    "region_rank": null
  },
  {
    "contentType": "airport",
    "datatype": "airport",
    "id": "32630",
    "ident": "FMMZ",
    "type": "small_airport",
    "name": "Ambatondrazaka Airport",
    "regionRef": "304623",
    "continentRef": "302549",
    "municipality": "Ambatondrazaka",
    "latitude_deg": "-17.795378",
    "longitude_deg": "48.442583",
    "elevation_ft": "2513",
    "magnetic_variation_deg": null,
    "icao_code": "FMMZ",
    "iata_code": "WAM",
    "gps_code": "FMMZ",
    "local_code": null,
    "has_scheduled_service": "0",
    "score": "150",
    "home_link": null,
    "wikipedia_link": "https://en.wikipedia.org/wiki/Ambatondrazaka_Airport",
    "pilot_link": null,
    "keywords": null,
    "zoom": "14",
    "changeMemberRef": "522325",
    "changeDate": "2025-02-05 19:09:19",
    "changeType": "update",
    "changeComment": null,
    "airportRef": "32630",
    "visitor_count": "0",
    "comment_count": "0",
    "home_count": "0",
    "region_code": "MG-A",
    "region_name": "Toamasina",
    "region_local_code": "A",
    "region_keywords": "Airports in Toamasina",
    "countryRef": "302585",
    "country_code": "MG",
    "country_name": "Madagascar",
    "country_keywords": "Airports in Madagascar",
    "continent_code": "AF",
    "continent_name": "Africa",
    "continent_keywords": "African airports",
    "has_metar": null,
    "has_taf": null,
    "world_rank": null,
    "continent_rank": null,
    "country_rank": null,
    "region_rank": null
  },
  {
    "contentType": "airport",
    "datatype": "airport",
    "id": "31688",
    "ident": "MG-0023",
    "type": "closed",
    "name": "Ambanja Airport",
    "regionRef": "304624",
    "continentRef": "302549",
    "municipality": "Ambanja",
    "latitude_deg": "-13.644528",
    "longitude_deg": "48.456595",
    "elevation_ft": "36",
    "magnetic_variation_deg": null,
    "icao_code": null,
    "iata_code": null,
    "gps_code": null,
    "local_code": null,
    "has_scheduled_service": "1",
    "score": "150",
    "home_link": null,
    "wikipedia_link": null,
    "pilot_link": null,
    "keywords": "FMNJ",
    "zoom": "14",
    "changeMemberRef": "504793",
    "changeDate": "2025-02-25 14:49:24",
    "changeType": "update",
    "changeComment": "Remove codes for closed airports.",
    "airportRef": "31688",
    "visitor_count": "0",
    "comment_count": "0",
    "home_count": "0",
    "region_code": "MG-D",
    "region_name": "Antsiranana",
    "region_local_code": "D",
    "region_keywords": "Airports in Antsiranana",
    "countryRef": "302585",
    "country_code": "MG",
    "country_name": "Madagascar",
    "country_keywords": "Airports in Madagascar",
    "continent_code": "AF",
    "continent_name": "Africa",
    "continent_keywords": "African airports",
    "has_metar": null,
    "has_taf": null,
    "world_rank": null,
    "continent_rank": null,
    "country_rank": null,
    "region_rank": null
  },
  {
    "contentType": "airport",
    "datatype": "airport",
    "id": "30951",
    "ident": "FMNO",
    "type": "small_airport",
    "name": "Soalala Airport",
    "regionRef": "304626",
    "continentRef": "302549",
    "municipality": "Soalala",
    "latitude_deg": "-16.10169",
    "longitude_deg": "45.358837",
    "elevation_ft": "141",
    "magnetic_variation_deg": null,
    "icao_code": "FMNO",
    "iata_code": "DWB",
    "gps_code": "FMNO",
    "local_code": null,
    "has_scheduled_service": "1",
    "score": "150",
    "home_link": null,
    "wikipedia_link": "https://en.wikipedia.org/wiki/Soalala_Airport",
    "pilot_link": null,
    "keywords": null,
    "zoom": "14",
    "changeMemberRef": "329245",
    "changeDate": "2018-09-16 03:17:48",
    "changeType": "update",
    "changeComment": null,
    "airportRef": "30951",
    "visitor_count": "0",
    "comment_count": "0",
    "home_count": "0",
    "region_code": "MG-M",
    "region_name": "Mahajanga",
    "region_local_code": "M",
    "region_keywords": "Airports in Mahajanga",
    "countryRef": "302585",
    "country_code": "MG",
    "country_name": "Madagascar",
    "country_keywords": "Airports in Madagascar",
    "continent_code": "AF",
    "continent_name": "Africa",
    "continent_keywords": "African airports",
    "has_metar": null,
    "has_taf": null,
    "world_rank": null,
    "continent_rank": null,
    "country_rank": null,
    "region_rank": null
  },
  {
    "contentType": "airport",
    "datatype": "airport",
    "id": "318417",
    "ident": "MG-0006",
    "type": "small_airport",
    "name": "Fotadrevo Airport",
    "regionRef": "304628",
    "continentRef": "302549",
    "municipality": "Fotadrevo",
    "latitude_deg": "-24.031299",
    "longitude_deg": "45.026573",
    "elevation_ft": null,
    "magnetic_variation_deg": null,
    "icao_code": null,
    "iata_code": null,
    "gps_code": null,
    "local_code": null,
    "has_scheduled_service": "0",
    "score": "50",
    "home_link": null,
    "wikipedia_link": null,
    "pilot_link": null,
    "keywords": null,
    "zoom": "14",
    "changeMemberRef": "317644",
    "changeDate": "2016-06-09 06:47:56",
    "changeType": "create",
    "changeComment": null,
    "airportRef": "318417",
    "visitor_count": "0",
    "comment_count": "0",
    "home_count": "0",
    "region_code": "MG-U",
    "region_name": "Toliara",
    "region_local_code": "U",
    "region_keywords": "Airports in Toliara",
    "countryRef": "302585",
    "country_code": "MG",
    "country_name": "Madagascar",
    "country_keywords": "Airports in Madagascar",
    "continent_code": "AF",
    "continent_name": "Africa",
    "continent_keywords": "African airports",
    "has_metar": null,
    "has_taf": null,
    "world_rank": null,
    "continent_rank": null,
    "country_rank": null,
    "region_rank": null
  },
  {
    "contentType": "airport",
    "datatype": "airport",
    "id": "318416",
    "ident": "MG-0005",
    "type": "small_airport",
    "name": "Itampolo Airport",
    "regionRef": "304628",
    "continentRef": "302549",
    "municipality": "Itampolo",
    "latitude_deg": "-24.691968",
    "longitude_deg": "43.950994",
    "elevation_ft": null,
    "magnetic_variation_deg": null,
    "icao_code": null,
    "iata_code": null,
    "gps_code": null,
    "local_code": null,
    "has_scheduled_service": "0",
    "score": "50",
    "home_link": null,
    "wikipedia_link": null,
    "pilot_link": null,
    "keywords": null,
    "zoom": "14",
    "changeMemberRef": "317644",
    "changeDate": "2016-06-09 06:45:42",
    "changeType": "create",
    "changeComment": null,
    "airportRef": "318416",
    "visitor_count": "0",
    "comment_count": "0",
    "home_count": "0",
    "region_code": "MG-U",
    "region_name": "Toliara",
    "region_local_code": "U",
    "region_keywords": "Airports in Toliara",
    "countryRef": "302585",
    "country_code": "MG",
    "country_name": "Madagascar",
    "country_keywords": "Airports in Madagascar",
    "continent_code": "AF",
    "continent_name": "Africa",
    "continent_keywords": "African airports",
    "has_metar": null,
    "has_taf": null,
    "world_rank": null,
    "continent_rank": null,
    "country_rank": null,
    "region_rank": null
  },
  {
    "contentType": "airport",
    "datatype": "airport",
    "id": "525175",
    "ident": "MG-0021",
    "type": "small_airport",
    "name": "Relais de la Reine Airport",
    "regionRef": "304629",
    "continentRef": "302549",
    "municipality": "Isalo",
    "latitude_deg": "-22.645343",
    "longitude_deg": "45.323914",
    "elevation_ft": null,
    "magnetic_variation_deg": null,
    "icao_code": null,
    "iata_code": "RLR",
    "gps_code": null,
    "local_code": null,
    "has_scheduled_service": "0",
    "score": "50",
    "home_link": null,
    "wikipedia_link": null,
    "pilot_link": null,
    "keywords": null,
    "zoom": "14",
    "changeMemberRef": "524349",
    "changeDate": "2024-04-09 16:19:40",
    "changeType": "create",
    "changeComment": null,
    "airportRef": "525175",
    "visitor_count": "0",
    "comment_count": "0",
    "home_count": "0",
    "region_code": "MG-U-A",
    "region_name": "(unassigned)",
    "region_local_code": "U-A",
    "region_keywords": "Airports in (unassigned)",
    "countryRef": "302585",
    "country_code": "MG",
    "country_name": "Madagascar",
    "country_keywords": "Airports in Madagascar",
    "continent_code": "AF",
    "continent_name": "Africa",
    "continent_keywords": "African airports",
    "has_metar": null,
    "has_taf": null,
    "world_rank": null,
    "continent_rank": null,
    "country_rank": null,
    "region_rank": null
  },
  {
    "contentType": "airport",
    "datatype": "airport",
    "id": "525780",
    "ident": "MG-0022",
    "type": "small_airport",
    "name": "Fihaonana Aerodrome",
    "regionRef": "304627",
    "continentRef": "302549",
    "municipality": "Analamanga",
    "latitude_deg": "-18.574666",
    "longitude_deg": "47.238588",
    "elevation_ft": "4511",
    "magnetic_variation_deg": null,
    "icao_code": null,
    "iata_code": null,
    "gps_code": null,
    "local_code": null,
    "has_scheduled_service": "0",
    "score": "50",
    "home_link": null,
    "wikipedia_link": null,
    "pilot_link": "https://mapcarta.com/14475374",
    "keywords": null,
    "zoom": "15",
    "changeMemberRef": "83281",
    "changeDate": "2024-05-04 14:13:28",
    "changeType": "update",
    "changeComment": "Added region.",
    "airportRef": "525780",
    "visitor_count": "0",
    "comment_count": "0",
    "home_count": "0",
    "region_code": "MG-T",
    "region_name": "Antananarivo",
    "region_local_code": "T",
    "region_keywords": "Airports in Antananarivo",
    "countryRef": "302585",
    "country_code": "MG",
    "country_name": "Madagascar",
    "country_keywords": "Airports in Madagascar",
    "continent_code": "AF",
    "continent_name": "Africa",
    "continent_keywords": "African airports",
    "has_metar": null,
    "has_taf": null,
    "world_rank": null,
    "continent_rank": null,
    "country_rank": null,
    "region_rank": null
  },
  {
    "contentType": "airport",
    "datatype": "airport",
    "id": "318415",
    "ident": "MG-0004",
    "type": "small_airport",
    "name": "Antanimora Airport",
    "regionRef": "304628",
    "continentRef": "302549",
    "municipality": "Antanimora",
    "latitude_deg": "-24.84006",
    "longitude_deg": "45.675457",
    "elevation_ft": null,
    "magnetic_variation_deg": null,
    "icao_code": null,
    "iata_code": null,
    "gps_code": null,
    "local_code": null,
    "has_scheduled_service": "0",
    "score": "50",
    "home_link": null,
    "wikipedia_link": null,
    "pilot_link": null,
    "keywords": null,
    "zoom": "14",
    "changeMemberRef": "317644",
    "changeDate": "2016-06-09 06:43:59",
    "changeType": "create",
    "changeComment": null,
    "airportRef": "318415",
    "visitor_count": "0",
    "comment_count": "0",
    "home_count": "0",
    "region_code": "MG-U",
    "region_name": "Toliara",
    "region_local_code": "U",
    "region_keywords": "Airports in Toliara",
    "countryRef": "302585",
    "country_code": "MG",
    "country_name": "Madagascar",
    "country_keywords": "Airports in Madagascar",
    "continent_code": "AF",
    "continent_name": "Africa",
    "continent_keywords": "African airports",
    "has_metar": null,
    "has_taf": null,
    "world_rank": null,
    "continent_rank": null,
    "country_rank": null,
    "region_rank": null
  },
  {
    "contentType": "airport",
    "datatype": "airport",
    "id": "318414",
    "ident": "MG-0003",
    "type": "small_airport",
    "name": "Amboasary Sud Airport",
    "regionRef": "304628",
    "continentRef": "302549",
    "municipality": "Amboasary Sud",
    "latitude_deg": "-25.075585",
    "longitude_deg": "46.393433",
    "elevation_ft": null,
    "magnetic_variation_deg": null,
    "icao_code": null,
    "iata_code": null,
    "gps_code": null,
    "local_code": null,
    "has_scheduled_service": "0",
    "score": "50",
    "home_link": null,
    "wikipedia_link": null,
    "pilot_link": null,
    "keywords": null,
    "zoom": "14",
    "changeMemberRef": "317644",
    "changeDate": "2016-06-09 06:42:25",
    "changeType": "create",
    "changeComment": null,
    "airportRef": "318414",
    "visitor_count": "0",
    "comment_count": "0",
    "home_count": "0",
    "region_code": "MG-U",
    "region_name": "Toliara",
    "region_local_code": "U",
    "region_keywords": "Airports in Toliara",
    "countryRef": "302585",
    "country_code": "MG",
    "country_name": "Madagascar",
    "country_keywords": "Airports in Madagascar",
    "continent_code": "AF",
    "continent_name": "Africa",
    "continent_keywords": "African airports",
    "has_metar": null,
    "has_taf": null,
    "world_rank": null,
    "continent_rank": null,
    "country_rank": null,
    "region_rank": null
  },
  {
    "contentType": "airport",
    "datatype": "airport",
    "id": "318121",
    "ident": "DVD",
    "type": "small_airport",
    "name": "Andavadoaka Airport",
    "regionRef": "304628",
    "continentRef": "302549",
    "municipality": "Andavadoaka",
    "latitude_deg": "-22.06608",
    "longitude_deg": "43.259573",
    "elevation_ft": "30",
    "magnetic_variation_deg": null,
    "icao_code": null,
    "iata_code": "DVD",
    "gps_code": null,
    "local_code": null,
    "has_scheduled_service": "0",
    "score": "50",
    "home_link": null,
    "wikipedia_link": "https://en.wikipedia.org/wiki/Andavadoaka_Airport",
    "pilot_link": null,
    "keywords": null,
    "zoom": "14",
    "changeMemberRef": "83281",
    "changeDate": "2016-05-28 16:27:55",
    "changeType": "create",
    "changeComment": null,
    "airportRef": "318121",
    "visitor_count": "0",
    "comment_count": "0",
    "home_count": "0",
    "region_code": "MG-U",
    "region_name": "Toliara",
    "region_local_code": "U",
    "region_keywords": "Airports in Toliara",
    "countryRef": "302585",
    "country_code": "MG",
    "country_name": "Madagascar",
    "country_keywords": "Airports in Madagascar",
    "continent_code": "AF",
    "continent_name": "Africa",
    "continent_keywords": "African airports",
    "has_metar": null,
    "has_taf": null,
    "world_rank": null,
    "continent_rank": null,
    "country_rank": null,
    "region_rank": null
  },
  {
    "contentType": "airport",
    "datatype": "airport",
    "id": "333231",
    "ident": "TZO",
    "type": "small_airport",
    "name": "Tsimiroro Airport",
    "regionRef": "304628",
    "continentRef": "302549",
    "municipality": "Ankisatra",
    "latitude_deg": "-18.345064",
    "longitude_deg": "45.015643",
    "elevation_ft": "755",
    "magnetic_variation_deg": null,
    "icao_code": null,
    "iata_code": "TZO",
    "gps_code": null,
    "local_code": null,
    "has_scheduled_service": "0",
    "score": "50",
    "home_link": null,
    "wikipedia_link": null,
    "pilot_link": null,
    "keywords": null,
    "zoom": "14",
    "changeMemberRef": "83281",
    "changeDate": "2020-02-09 21:18:37",
    "changeType": "create",
    "changeComment": null,
    "airportRef": "333231",
    "visitor_count": "0",
    "comment_count": "0",
    "home_count": "0",
    "region_code": "MG-U",
    "region_name": "Toliara",
    "region_local_code": "U",
    "region_keywords": "Airports in Toliara",
    "countryRef": "302585",
    "country_code": "MG",
    "country_name": "Madagascar",
    "country_keywords": "Airports in Madagascar",
    "continent_code": "AF",
    "continent_name": "Africa",
    "continent_keywords": "African airports",
    "has_metar": null,
    "has_taf": null,
    "world_rank": null,
    "continent_rank": null,
    "country_rank": null,
    "region_rank": null
  },
  {
    "contentType": "airport",
    "datatype": "airport",
    "id": "318422",
    "ident": "MG-0011",
    "type": "small_airport",
    "name": "Maromby Airport",
    "regionRef": "304628",
    "continentRef": "302549",
    "municipality": "Maromby",
    "latitude_deg": "-24.382498",
    "longitude_deg": "46.556238",
    "elevation_ft": null,
    "magnetic_variation_deg": null,
    "icao_code": null,
    "iata_code": null,
    "gps_code": null,
    "local_code": null,
    "has_scheduled_service": "0",
    "score": "50",
    "home_link": null,
    "wikipedia_link": null,
    "pilot_link": null,
    "keywords": null,
    "zoom": "14",
    "changeMemberRef": "317644",
    "changeDate": "2016-06-09 07:17:16",
    "changeType": "create",
    "changeComment": null,
    "airportRef": "318422",
    "visitor_count": "0",
    "comment_count": "0",
    "home_count": "0",
    "region_code": "MG-U",
    "region_name": "Toliara",
    "region_local_code": "U",
    "region_keywords": "Airports in Toliara",
    "countryRef": "302585",
    "country_code": "MG",
    "country_name": "Madagascar",
    "country_keywords": "Airports in Madagascar",
    "continent_code": "AF",
    "continent_name": "Africa",
    "continent_keywords": "African airports",
    "has_metar": null,
    "has_taf": null,
    "world_rank": null,
    "continent_rank": null,
    "country_rank": null,
    "region_rank": null
  },
  {
    "contentType": "airport",
    "datatype": "airport",
    "id": "30642",
    "ident": "FMSY",
    "type": "small_airport",
    "name": "Ampanihy Airport",
    "regionRef": "304628",
    "continentRef": "302549",
    "municipality": "Ampanihy",
    "latitude_deg": "-24.699699",
    "longitude_deg": "44.7342",
    "elevation_ft": "771",
    "magnetic_variation_deg": null,
    "icao_code": "FMSY",
    "iata_code": "AMP",
    "gps_code": "FMSY",
    "local_code": null,
    "has_scheduled_service": "0",
    "score": "50",
    "home_link": null,
    "wikipedia_link": "https://en.wikipedia.org/wiki/Ampanihy_Airport",
    "pilot_link": null,
    "keywords": null,
    "zoom": "14",
    "changeMemberRef": "524349",
    "changeDate": "2024-04-07 06:08:27",
    "changeType": "update",
    "changeComment": null,
    "airportRef": "30642",
    "visitor_count": "0",
    "comment_count": "0",
    "home_count": "0",
    "region_code": "MG-U",
    "region_name": "Toliara",
    "region_local_code": "U",
    "region_keywords": "Airports in Toliara",
    "countryRef": "302585",
    "country_code": "MG",
    "country_name": "Madagascar",
    "country_keywords": "Airports in Madagascar",
    "continent_code": "AF",
    "continent_name": "Africa",
    "continent_keywords": "African airports",
    "has_metar": null,
    "has_taf": null,
    "world_rank": null,
    "continent_rank": null,
    "country_rank": null,
    "region_rank": null
  }
]
