[
  {
    "name": "Rota International Airport",
    "code": "5430",
    "type": "medium_airport",
    "location": "Rota Island",
    "country_id": "302771",
    "country_code": "MP",
    "IATA": "ROP",
    "ICAO": "PGRO",
    "Latitude": "14.1743",
    "Longitude": "145.242996",
    "Altitude": "607",
    "EDI": null
  },
  {
    "name": "Saipan International Airport",
    "code": "5431",
    "type": "medium_airport",
    "location": "I Fadang, Saipan",
    "country_id": "302771",
    "country_code": "MP",
    "IATA": "SPN",
    "ICAO": "PGSN",
    "Latitude": "15.119",
    "Longitude": "145.729004",
    "Altitude": "215",
    "EDI": null
  },
  {
    "name": "Tinian International Airport",
    "code": "5434",
    "type": "medium_airport",
    "location": "Tinian Island",
    "country_id": "302771",
    "country_code": "MP",
    "IATA": "TIQ",
    "ICAO": "PGWT",
    "Latitude": "14.998101",
    "Longitude": "145.61923",
    "Altitude": "271",
    "EDI": null
  },
  {
    "name": "Pagan Airstrip",
    "code": "4783",
    "type": "small_airport",
    "location": "Shomu-Shon, Pagan",
    "country_id": "302771",
    "country_code": "MP",
    "IATA": null,
    "ICAO": null,
    "Latitude": "18.12317",
    "Longitude": "145.763347",
    "Altitude": "34",
    "EDI": null
  },
  {
    "name": "Dynasty Heliport",
    "code": "4777",
    "type": "heliport",
    "location": "San Jose, Tinian",
    "country_id": "302771",
    "country_code": "MP",
    "IATA": null,
    "ICAO": null,
    "Latitude": "14.960012",
    "Longitude": "145.631075",
    "Altitude": "150",
    "EDI": null
  },
  {
    "name": "Commonwealth Health Center Heliport",
    "code": "4778",
    "type": "heliport",
    "location": "Garapan, Saipan",
    "country_id": "302771",
    "country_code": "MP",
    "IATA": null,
    "ICAO": null,
    "Latitude": "15.209759",
    "Longitude": "145.72457",
    "Altitude": "16",
    "EDI": null
  },
  {
    "name": "Tinian Heliport",
    "code": "4780",
    "type": "heliport",
    "location": "San Jose, Tinian",
    "country_id": "302771",
    "country_code": "MP",
    "IATA": null,
    "ICAO": null,
    "Latitude": "14.963692",
    "Longitude": "145.627127",
    "Altitude": "75",
    "EDI": null
  },
  {
    "name": "Coral Ocean Point Pro-Shop Heliport",
    "code": "4781",
    "type": "heliport",
    "location": "Koblerville, Saipan",
    "country_id": "302771",
    "country_code": "MP",
    "IATA": null,
    "ICAO": null,
    "Latitude": "15.114978",
    "Longitude": "145.701649",
    "Altitude": "125",
    "EDI": null
  },
  {
    "name": "Tinian Dynasty Heliport",
    "code": "4782",
    "type": "heliport",
    "location": "San Jose, Tinian",
    "country_id": "302771",
    "country_code": "MP",
    "IATA": null,
    "ICAO": null,
    "Latitude": "14.962748",
    "Longitude": "145.629863",
    "Altitude": "175",
    "EDI": null
  },
  {
    "name": "Nikko Heliport",
    "code": "4784",
    "type": "heliport",
    "location": "San Roque, Saipan",
    "country_id": "302771",
    "country_code": "MP",
    "IATA": null,
    "ICAO": null,
    "Latitude": "15.25",
    "Longitude": "145.783005",
    "Altitude": "60",
    "EDI": null
  },
  {
    "name": "Gualo Rai Heliport",
    "code": "4785",
    "type": "heliport",
    "location": "Gualo Rai, Saipan",
    "country_id": "302771",
    "country_code": "MP",
    "IATA": null,
    "ICAO": null,
    "Latitude": "15.188155",
    "Longitude": "145.724157",
    "Altitude": "250",
    "EDI": null
  },
  {
    "name": "Tinian North Field",
    "code": "351420",
    "type": "closed",
    "location": "San Jose, Tinian",
    "country_id": "302771",
    "country_code": "MP",
    "IATA": null,
    "ICAO": null,
    "Latitude": "15.07242",
    "Longitude": "145.6382",
    "Altitude": "150",
    "EDI": null
  }
]