[
  {
    "name": "Lungi International Airport",
    "code": "3095",
    "type": "large_airport",
    "location": "Freetown (Lungi-Town)",
    "country_id": "302599",
    "country_code": "SL",
    "IATA": "FNA",
    "ICAO": "GFLL",
    "Latitude": "8.61644",
    "Longitude": "-13.1955",
    "Altitude": "84",
    "EDI": null
  },
  {
    "name": "Kenema Airport",
    "code": "31741",
    "type": "medium_airport",
    "location": "Kenema",
    "country_id": "302599",
    "country_code": "SL",
    "IATA": "KEN",
    "ICAO": "GFKE",
    "Latitude": "7.896364",
    "Longitude": "-11.174126",
    "Altitude": "485",
    "EDI": null
  },
  {
    "name": "Yengema Airport",
    "code": "32689",
    "type": "medium_airport",
    "location": "Yengema",
    "country_id": "302599",
    "country_code": "SL",
    "IATA": "WYE",
    "ICAO": "GFYE",
    "Latitude": "8.61047",
    "Longitude": "-11.0454",
    "Altitude": "1300",
    "EDI": null
  },
  {
    "name": "Bo Airport",
    "code": "31728",
    "type": "medium_airport",
    "location": "Bo",
    "country_id": "302599",
    "country_code": "SL",
    "IATA": "KBS",
    "ICAO": "GFBO",
    "Latitude": "7.9444",
    "Longitude": "-11.761",
    "Altitude": "328",
    "EDI": null
  },
  {
    "name": "Sherbro International Airport",
    "code": "30799",
    "type": "closed",
    "location": "Bonthe",
    "country_id": "302599",
    "country_code": "SL",
    "IATA": null,
    "ICAO": null,
    "Latitude": "7.53242",
    "Longitude": "-12.5189",
    "Altitude": "14",
    "EDI": null
  },
  {
    "name": "Tongo Airport",
    "code": "31526",
    "type": "small_airport",
    "location": "Tongo",
    "country_id": "302599",
    "country_code": "SL",
    "IATA": null,
    "ICAO": null,
    "Latitude": "8.217000007629395",
    "Longitude": "-11.067000389099121",
    "Altitude": "750",
    "EDI": null
  },
  {
    "name": "Kabala Airport",
    "code": "31721",
    "type": "small_airport",
    "location": "Kabala",
    "country_id": "302599",
    "country_code": "SL",
    "IATA": "KBA",
    "ICAO": "GFKB",
    "Latitude": "9.638322913429999",
    "Longitude": "-11.5155601501",
    "Altitude": "1012",
    "EDI": null
  },
  {
    "name": "Gbangbatok Airport",
    "code": "31517",
    "type": "small_airport",
    "location": "Gbangbatok",
    "country_id": "302599",
    "country_code": "SL",
    "IATA": "GBK",
    "ICAO": "GFGK",
    "Latitude": "7.812535",
    "Longitude": "-12.377815",
    "Altitude": "75",
    "EDI": null
  },
  {
    "name": "Hastings Airport",
    "code": "31525",
    "type": "small_airport",
    "location": "Freetown",
    "country_id": "302599",
    "country_code": "SL",
    "IATA": "HGS",
    "ICAO": "GFHA",
    "Latitude": "8.394348",
    "Longitude": "-13.128891",
    "Altitude": "60",
    "EDI": null
  },
  {
    "name": "Mammy Yoko Heliport",
    "code": "301111",
    "type": "heliport",
    "location": null,
    "country_id": "302599",
    "country_code": "SL",
    "IATA": null,
    "ICAO": null,
    "Latitude": "8.49231124864",
    "Longitude": "-13.2884573936",
    "Altitude": null,
    "EDI": null
  },
  {
    "name": "RSLAF Cockerill Barracks Heliport",
    "code": "308901",
    "type": "heliport",
    "location": "Freetown",
    "country_id": "302599",
    "country_code": "SL",
    "IATA": null,
    "ICAO": null,
    "Latitude": "8.473991",
    "Longitude": "-13.277643",
    "Altitude": null,
    "EDI": null
  },
  {
    "name": "UN Aviation Heliport",
    "code": "308902",
    "type": "heliport",
    "location": null,
    "country_id": "302599",
    "country_code": "SL",
    "IATA": null,
    "ICAO": null,
    "Latitude": "8.48768473679",
    "Longitude": "-13.288103342100001",
    "Altitude": null,
    "EDI": null
  }
]